Workbook

Sheet Repair Assessment Sheet
A2: MOHD.YAMIN | C2: MOHD YAMIN
C5: Surveyor & Loss Assessor
C6: IRDA Iicense No.72970 valid upto 23/08/2026
C8: REPAIR ASSESSMENT / PROCESSING SHEET
C10: Date of Survey | H10: Date of Allotment of Claim | O10: Date of submission of final report
C12: Insured's Details | O12: Loss Details
C13: NAME | O13: Claim Number:
D14: First name | H14: Last name | O14: Place & time of Accident
O15: Place of survey | AA15: Not exceeding 6 months | AE15: Nill Depreciation on paint labour | AJ15: Plastic/Rubber | AK15: NA | AL15: Front | AM15: Repair | AO15: YES
O16: Date Of Loss : | Y16: 41306 | AA16: Exceeding 6 months but not exceeding1 year | AC16: Self Attested | AE16: If labour consolidated @25% | AJ16: Metal | AK16: Left | AL16: Center | AM16: Replace | AO16: NO
C17: Policy Number: | O17: CBC : | Q17: =IF((DAYS360(E18,Q16))<30,"CBC REQUIRED","CBC Cleared") -> CBC REQUIRED | Y17: 41015 | AA17: Exceeding 1 year but not exceeding 2 years | AC17: YES | AE17: If Paint Bifurcation Available Dep applied 50% | AJ17: Glass | AK17: Right | AL17: Rear | AM17: Remove/Install | AO17: N/A
C18: Policy Period : | G18: TO | O18: Close Promity: | Q18: =IF((DAYS360(E18,Q16))<15,"Close Proximity","CPCleared") -> Close Proximity | AA18: Exceeding 2 years but not exceeding 3 years | AC18: NO | AE18: If Paint labour consolidated @25% | AJ18: Fiber Glass
C19: Present address if other than Policy Address | O19: Potential Case for Bodily Injury | R19: NO | Y19: 250 | AA19: Exceeding 3 years but not exceeding 4 years | AC19: Not applicable | AE19: Dep on paint not applicable | AJ19: Consumables
AA20: Exceeding 4 years but not exceeding 5 years | AE20: If paint labour consolidated @25% | AJ20: Engine Secure
C21: Vehicle Details | O21: Drivers Details | U21: 41015 | AA21: Exceeding 5 years but not exceeding 10 years | AE21: If labour consolidated @25% | AJ21: Tyre Secure
C22: Vehicle Regn Number: | H22: YES | N22: Drivers Name: | R22: Age: | AA22: Exceeding 10 years | AE22: If Paint Bifurcation Available Dep applied @50% | AJ22: Key Replacement
C23: Odometer Reading | H23: As Per RC | N23: License No: | R23: Lic. Authority | AA23: NA | AE23: =(Q70+R70+S70) -> 0
C24: Make : | F24: Chassis Number : | N24: Effective upto: | R24: Effective for: | AA24: Dep Reimbursment | AE24: =IF(C82=AE15,0,IF(C82=AE16,0,IF(C82=AE17,AE23*70%,IF(C82=AE18,AE23*75%,IF(C82=AE20,0,IF(C82=AE22,0,IF(C82=AE21,AE23*25%,IF(C82=AE19,0)))))))) -> 0 | AF24: =IF(H26<350,250,0) -> 250
C25: Model: | F25: Engine Number : | R25: Yrs. Of Driving | AA25: NA | AE25: =IF(C82=AE15,0,IF(C82=AE16,0,IF(C82=AE17,AE24*H35%,IF(C82=AE18,AE24*H35%,IF(C82=AE20,0,IF(C82=AE22,0,IF(C82=AE21,AE24*50%,IF(C82=AE19,0)))))))) -> 0 | AF25: =IF(P84=AA24,AF24,IF(P84=AA23,AG24)) -> 250
C26: Date of Regn: | F26: Cubic Capacity : | H26: 0 | O26: DL Verified | Q26: YES | AA26: Consumabels | AE26: =(S70*25%*50%) -> 0 | AF26: =(S70*75%)*H35% -> 0
C27: Color of vehicle | AA27: Consumabels With dep cap
E28: As per Actual | Q28: Check
D29: Vehicle Regn no. | E29: =E22 -> 0 | O29: Pre Inspection | Q29: NO | AA29: =G37 -> 0
D30: Chassis no. | E30: =H24 -> 0 | O30: previous claim | Q30: NO | AA30: INSURED
D31: Engine no. | E31: =H25 -> 0
C32: Cause of loss:- | O32: Observations:-
H34: % Depreciation on metals
C35: Exceeding 6 months but not exceeding1 year | H35: =IF(C35=AA15,0,IF(C35=AA16,5,IF(C35=AA17,10,IF(C35=AA18,15,IF(C35=AA19,25,IF(C35=AA20,35,IF(C35=AA21,40,IF(C35=AA22,50)))))))) -> 5 | J35: =DATEDIF(E26,Q16,"Y")&"Years"""&DATEDIF(E26,Q16,"YM")&"Months" -> 0Years"0Months | P35: Reserve:
C37: Name of the Garage: | G37: =Q15 -> 0 | P37: Reinspected On:
C39: Surveyed By: | G39: MOHD YAMIN | O39: In House Adjuster : | Q39: =G39 -> MOHD YAMIN
C42: Sr.No | D42: Repair/Replace | E42: Description | J42: Parts@list | K42: SGST | L42: CGST | M42: SGST AM | N42: CGST AM | O42: Depn in % | P42: Net Amount | Q42: Labour Remove& Refit | R42: Labour Repair | S42: Paint | T42: HSN Code
E43: Material | G43: Section | H43: Parts
C44: 1 | K44: 0 | L44: =K44 -> 0 | M44: =J44*K44 -> 0 | N44: =J44*L44 -> 0 | O44: =IF(E44=AA$43,0,IF(E44=AJ$16,H$35,IF(E44=AJ$17,0,IF(E44=AJ$15,50, IF(E44=AJ$18,0,IF(E44=AJ$19,0)))))) -> 0 | P44: =J44+M44+N44-(J44+M44+N44)*O44% -> 0 | T44: =[1]Sheet1!E2 -> 85072000 | V44: =[1]Sheet1!L2 -> 0.28
C45: 2 | K45: 0 | L45: =K45 -> 0 | M45: =J45*K45 -> 0 | N45: =J45*L45 -> 0 | O45: =IF(E45=AA$43,0,IF(E45=AJ$16,H$35,IF(E45=AJ$17,0,IF(E45=AJ$15,50, IF(E45=AJ$18,0,IF(E45=AJ$19,0)))))) -> 0 | P45: =J45+M45+N45-(J45+M45+N45)*O45% -> 0 | T45: =[1]Sheet1!E3 -> 85443000 | V45: =[1]Sheet1!L3 -> 0.18
C46: 3 | K46: 0 | L46: =K46 -> 0 | M46: =J46*K46 -> 0 | N46: =J46*L46 -> 0 | O46: =IF(E46=AA$43,0,IF(E46=AJ$16,H$35,IF(E46=AJ$17,0,IF(E46=AJ$15,50, IF(E46=AJ$18,0,IF(E46=AJ$19,0)))))) -> 0 | P46: =J46+M46+N46-(J46+M46+N46)*O46% -> 0 | T46: =[1]Sheet1!E4 -> 87089900 | V46: =[1]Sheet1!L4 -> 0.28
C47: 4 | K47: 0 | L47: =K47 -> 0 | M47: =J47*K47 -> 0 | N47: =J47*L47 -> 0 | O47: =IF(E47=AA$43,0,IF(E47=AJ$16,H$35,IF(E47=AJ$17,0,IF(E47=AJ$15,50, IF(E47=AJ$18,0,IF(E47=AJ$19,0)))))) -> 0 | P47: =J47+M47+N47-(J47+M47+N47)*O47% -> 0 | T47: =[1]Sheet1!E5 -> 40169340 | V47: =[1]Sheet1!L5 -> 0.18
C48: 5 | K48: 0 | L48: =K48 -> 0 | M48: =J48*K48 -> 0 | N48: =J48*L48 -> 0 | O48: =IF(E48=AA$43,0,IF(E48=AJ$16,H$35,IF(E48=AJ$17,0,IF(E48=AJ$15,50, IF(E48=AJ$18,0,IF(E48=AJ$19,0)))))) -> 0 | P48: =J48+M48+N48-(J48+M48+N48)*O48% -> 0 | T48: =[1]Sheet1!E6 -> 40169340 | V48: =[1]Sheet1!L6 -> 0.18
C49: 6 | K49: 0 | L49: =K49 -> 0 | M49: =J49*K49 -> 0 | N49: =J49*L49 -> 0 | O49: =IF(E49=AA$43,0,IF(E49=AJ$16,H$35,IF(E49=AJ$17,0,IF(E49=AJ$15,50, IF(E49=AJ$18,0,IF(E49=AJ$19,0)))))) -> 0 | P49: =J49+M49+N49-(J49+M49+N49)*O49% -> 0 | T49: =[1]Sheet1!E7 -> 40094200 | V49: =[1]Sheet1!L7 -> 0.18
C50: 7 | K50: 0 | L50: =K50 -> 0 | M50: =J50*K50 -> 0 | N50: =J50*L50 -> 0 | O50: =IF(E50=AA$43,0,IF(E50=AJ$16,H$35,IF(E50=AJ$17,0,IF(E50=AJ$15,50, IF(E50=AJ$18,0,IF(E50=AJ$19,0)))))) -> 0 | P50: =J50+M50+N50-(J50+M50+N50)*O50% -> 0 | T50: =[1]Sheet1!E8 -> 40094200 | V50: =[1]Sheet1!L8 -> 0.18
C51: 8 | K51: 0 | L51: =K51 -> 0 | M51: =J51*K51 -> 0 | N51: =J51*L51 -> 0 | O51: =IF(E51=AA$43,0,IF(E51=AJ$16,H$35,IF(E51=AJ$17,0,IF(E51=AJ$15,50, IF(E51=AJ$18,0,IF(E51=AJ$19,0)))))) -> 0 | P51: =J51+M51+N51-(J51+M51+N51)*O51% -> 0 | T51: =[1]Sheet1!E9 -> 84213100 | V51: =[1]Sheet1!L9 -> 0.18
C52: 9 | K52: 0 | L52: =K52 -> 0 | M52: =J52*K52 -> 0 | N52: =J52*L52 -> 0 | O52: =IF(E52=AA$43,0,IF(E52=AJ$16,H$35,IF(E52=AJ$17,0,IF(E52=AJ$15,50, IF(E52=AJ$18,0,IF(E52=AJ$19,0)))))) -> 0 | P52: =J52+M52+N52-(J52+M52+N52)*O52% -> 0 | T52: =[1]Sheet1!E10 -> 40094200 | V52: =[1]Sheet1!L10 -> 0.18
C53: 10 | K53: 0 | L53: =K53 -> 0 | M53: =J53*K53 -> 0 | N53: =J53*L53 -> 0 | O53: =IF(E53=AA$43,0,IF(E53=AJ$16,H$35,IF(E53=AJ$17,0,IF(E53=AJ$15,50, IF(E53=AJ$18,0,IF(E53=AJ$19,0)))))) -> 0 | P53: =J53+M53+N53-(J53+M53+N53)*O53% -> 0 | T53: =[1]Sheet1!E11 -> 84099990 | V53: =[1]Sheet1!L11 -> 0.28
C54: 11 | K54: 0 | L54: =K54 -> 0 | M54: =J54*K54 -> 0 | N54: =J54*L54 -> 0 | O54: =IF(E54=AA$43,0,IF(E54=AJ$16,H$35,IF(E54=AJ$17,0,IF(E54=AJ$15,50, IF(E54=AJ$18,0,IF(E54=AJ$19,0)))))) -> 0 | P54: =J54+M54+N54-(J54+M54+N54)*O54% -> 0 | T54: =[1]Sheet1!E12 -> 40094200 | V54: =[1]Sheet1!L12 -> 0.18
C55: 12 | K55: 0 | L55: =K55 -> 0 | M55: =J55*K55 -> 0 | N55: =J55*L55 -> 0 | O55: =IF(E55=AA$43,0,IF(E55=AJ$16,H$35,IF(E55=AJ$17,0,IF(E55=AJ$15,50, IF(E55=AJ$18,0,IF(E55=AJ$19,0)))))) -> 0 | P55: =J55+M55+N55-(J55+M55+N55)*O55% -> 0 | T55: =[1]Sheet1!E13 -> 87089900 | V55: =[1]Sheet1!L13 -> 0.28
C56: 13 | K56: 0 | L56: =K56 -> 0 | M56: =J56*K56 -> 0 | N56: =J56*L56 -> 0 | O56: =IF(E56=AA$43,0,IF(E56=AJ$16,H$35,IF(E56=AJ$17,0,IF(E56=AJ$15,50, IF(E56=AJ$18,0,IF(E56=AJ$19,0)))))) -> 0 | P56: =J56+M56+N56-(J56+M56+N56)*O56% -> 0 | T56: =[1]Sheet1!E15 -> 85115000 | V56: =[1]Sheet1!L15 -> 0.28
C57: 14 | K57: 0 | L57: =K57 -> 0 | M57: =J57*K57 -> 0 | N57: =J57*L57 -> 0 | O57: =IF(E57=AA$43,0,IF(E57=AJ$16,H$35,IF(E57=AJ$17,0,IF(E57=AJ$15,50, IF(E57=AJ$18,0,IF(E57=AJ$19,0)))))) -> 0 | P57: =J57+M57+N57-(J57+M57+N57)*O57% -> 0 | T57: =[1]Sheet1!E16 -> 84818090 | V57: =[1]Sheet1!L16 -> 0.18
C58: 15 | K58: 0 | L58: =K58 -> 0 | M58: =J58*K58 -> 0 | N58: =J58*L58 -> 0 | O58: =IF(E58=AA$43,0,IF(E58=AJ$16,H$35,IF(E58=AJ$17,0,IF(E58=AJ$15,50, IF(E58=AJ$18,0,IF(E58=AJ$19,0)))))) -> 0 | P58: =J58+M58+N58-(J58+M58+N58)*O58% -> 0 | T58: =[1]Sheet1!E17 -> 87089900 | V58: =[1]Sheet1!L17 -> 0.28
C59: 16 | K59: 0 | L59: =K59 -> 0 | M59: =J59*K59 -> 0 | N59: =J59*L59 -> 0 | O59: =IF(E59=AA$43,0,IF(E59=AJ$16,H$35,IF(E59=AJ$17,0,IF(E59=AJ$15,50, IF(E59=AJ$18,0,IF(E59=AJ$19,0)))))) -> 0 | P59: =J59+M59+N59-(J59+M59+N59)*O59% -> 0 | T59: =[1]Sheet1!E18 -> 84099990 | V59: =[1]Sheet1!L18 -> 0.28
C60: 17 | K60: 0 | L60: =K60 -> 0 | M60: =J60*K60 -> 0 | N60: =J60*L60 -> 0 | O60: =IF(E60=AA$43,0,IF(E60=AJ$16,H$35,IF(E60=AJ$17,0,IF(E60=AJ$15,50, IF(E60=AJ$18,0,IF(E60=AJ$19,0)))))) -> 0 | P60: =J60+M60+N60-(J60+M60+N60)*O60% -> 0 | T60: =[1]Sheet1!E19 -> 73269099 | V60: =[1]Sheet1!L19 -> 0.28
C61: 18 | K61: 0 | L61: =K61 -> 0 | M61: =J61*K61 -> 0 | N61: =J61*L61 -> 0 | O61: =IF(E61=AA$43,0,IF(E61=AJ$16,H$35,IF(E61=AJ$17,0,IF(E61=AJ$15,50, IF(E61=AJ$18,0,IF(E61=AJ$19,0)))))) -> 0 | P61: =J61+M61+N61-(J61+M61+N61)*O61% -> 0 | T61: =[1]Sheet1!E20 -> 40169990 | V61: =[1]Sheet1!L20 -> 0.18
C62: 19 | K62: 0 | L62: =K62 -> 0 | M62: =J62*K62 -> 0 | N62: =J62*L62 -> 0 | O62: =IF(E62=AA$43,0,IF(E62=AJ$16,H$35,IF(E62=AJ$17,0,IF(E62=AJ$15,50, IF(E62=AJ$18,0,IF(E62=AJ$19,0)))))) -> 0 | P62: =J62+M62+N62-(J62+M62+N62)*O62% -> 0 | T62: =[1]Sheet1!E21 -> 40169990 | V62: =[1]Sheet1!L21 -> 0.18
C63: 20 | K63: 0 | L63: =K63 -> 0 | M63: =J63*K63 -> 0 | N63: =J63*L63 -> 0 | O63: =IF(E63=AA$43,0,IF(E63=AJ$16,H$35,IF(E63=AJ$17,0,IF(E63=AJ$15,50, IF(E63=AJ$18,0,IF(E63=AJ$19,0)))))) -> 0 | P63: =J63+M63+N63-(J63+M63+N63)*O63% -> 0 | T63: =[1]Sheet1!E22 -> 87089900 | V63: =[1]Sheet1!L22 -> 0.28
C64: 21 | K64: 0 | L64: =K64 -> 0 | M64: =J64*K64 -> 0 | N64: =J64*L64 -> 0 | O64: =IF(E64=AA$43,0,IF(E64=AJ$16,H$35,IF(E64=AJ$17,0,IF(E64=AJ$15,50, IF(E64=AJ$18,0,IF(E64=AJ$19,0)))))) -> 0 | P64: =J64+M64+N64-(J64+M64+N64)*O64% -> 0 | T64: =[1]Sheet1!E23 -> 73182200 | V64: =[1]Sheet1!L23 -> 0.28
C65: 22 | K65: 0 | L65: =K65 -> 0 | M65: =J65*K65 -> 0 | N65: =J65*L65 -> 0 | O65: =IF(E65=AA$43,0,IF(E65=AJ$16,H$35,IF(E65=AJ$17,0,IF(E65=AJ$15,50, IF(E65=AJ$18,0,IF(E65=AJ$19,0)))))) -> 0 | P65: =J65+M65+N65-(J65+M65+N65)*O65% -> 0 | T65: =[1]Sheet1!E24 -> 84133090 | V65: =[1]Sheet1!L24 -> 0.28
C66: 23 | K66: 0 | L66: =K66 -> 0 | M66: =J66*K66 -> 0 | N66: =J66*L66 -> 0 | O66: =IF(E66=AA$43,0,IF(E66=AJ$16,H$35,IF(E66=AJ$17,0,IF(E66=AJ$15,50, IF(E66=AJ$18,0,IF(E66=AJ$19,0)))))) -> 0 | P66: =J66+M66+N66-(J66+M66+N66)*O66% -> 0 | T66: =[1]Sheet1!E25 -> 73269099 | V66: =[1]Sheet1!L25 -> 0.18
C67: 24 | K67: 0 | L67: =K67 -> 0 | M67: =J67*K67 -> 0 | N67: =J67*L67 -> 0 | O67: =IF(E67=AA$43,0,IF(E67=AJ$16,H$35,IF(E67=AJ$17,0,IF(E67=AJ$15,50, IF(E67=AJ$18,0,IF(E67=AJ$19,0)))))) -> 0 | P67: =J67+M67+N67-(J67+M67+N67)*O67% -> 0 | T67: =[1]Sheet1!E26 -> 73181900 | V67: =[1]Sheet1!L26 -> 0.18
C68: 25 | K68: 0 | L68: =K68 -> 0 | M68: =J68*K68 -> 0 | N68: =J68*L68 -> 0 | O68: =IF(E68=AA$43,0,IF(E68=AJ$16,H$35,IF(E68=AJ$17,0,IF(E68=AJ$15,50, IF(E68=AJ$18,0,IF(E68=AJ$19,0)))))) -> 0 | P68: =J68+M68+N68-(J68+M68+N68)*O68% -> 0
J69: 0 | K69: 0 | L69: =K69 -> 0 | M69: =J69*K69 -> 0 | N69: =J69*L69 -> 0 | O69: =IF(E69=AA$43,0,IF(E69=AJ$15,H$35,IF(E69=AJ$16,0,IF(E69=AJ$17,50, IF(E69=AJ$18,50,IF(E69=AJ$19,0)))))) -> 0 | P69: =J69+M69+N69-(J69+M69+N69)*O69% -> 0 | R69: 0
I70: Total | J70: =SUM(J44:J69) -> 0 | M70: =SUM(M44:M69) -> 0 | N70: =SUM(N44:N69) -> 0 | P70: =SUM(P44:P69) -> 0 | Q70: =SUM(Q44:Q69) -> 0 | R70: =SUM(R44:R69) -> 0 | S70: =SUM(S44:S69) -> 0 | T70: =SUM(Q70:S70) -> 0
B71: *This assessment is subject to terms and conditions in the policy and verification of all documents with the claim. Salvage has been destroyed.
C73: Summarized Report
C74: Discription | E74: Net Amout in INR | F74: SGST AM | G74: CGST AM | H74: Discount | I74: Discounted AM INR | J74: Net Payble INR | P74: Insured's Share | W74: =IF(H26<351,+IF(#REF!=AA23,0,250),+IF(#REF!=AA23,0,0)) -> #REF!
C75: Parts @ List Rs. | E75: =J70 -> 0 | F75: =M70 -> 0 | G75: =N70 -> 0 | H75: 0 | I75: =(E75*H75) -> 0 | J75: =E75+F75+G75-I75 -> 0 | P75: Depreciated amt. incl. taxes on Paint | S75: =J82 -> 0
C76: Depreciatied parts After taxes | E76: =J75-P70 -> 0 | H76: 0 | I76: =(E76*H76) -> 0 | J76: =E76+F76+G76-I76 -> 0 | P76: Depreciated Parts Amount with tax | S76: =J76 -> 0
C77: Consumable parts | E77: =SUMIF(E44:E69,"Consumables",J44:J69) -> 0 | F77: =SUMIF(E44:E69,"consumables",M44:M69) -> 0 | G77: =SUMIF(E44:E69,"consumables",N44:N69) -> 0 | H77: 0 | I77: =(E77*H77) -> 0 | J77: =E77+F77+G77 -> 0 | P77: Add Voulantry Excess | S77: =E85 -> 0
C78: Total Parts approved | E78: =J75-E76-J77 -> 0 | H78: 0 | I78: =(E78*H78) -> 0 | J78: =J75-J76-J77 -> 0 | P78: Add Compulsory Excess | S78: =E86 -> 1000
F79: SGST IN % | G79: CGST IN %
C80: Labour R&R & repair | E80: =(Q70+R70) -> 0 | F80: 9 | G80: 9 | H80: 0 | I80: =(E80*H80) -> 0 | J80: =E80+(E80*F80%)+(E80*G80%) -> 0 | P80: Total Insured's Share | S80: =SUM(S75:S78) -> 1000
C81: Paint Material | E81: =S70 -> 0 | F81: =F80 -> 9 | G81: =G80 -> 9 | H81: 0 | I81: =(E81*H81) -> 0 | J81: =E81+(E81*F81%)+(E81*G81%) -> 0
C82: If Paint labour consolidated @25% | E82: =IF(C82=AE15,0,IF(C82=AE16,(E80+E81)*12.5%,IF(C82=AE17,S70*50%,IF(C82=AE18,S70*12.5%,)))) -> 0 | F82: =F80 -> 9 | G82: =G80 -> 9 | H82: 0 | I82: =(E82*H82) -> 0 | J82: =E82+(E82*F82%)+(E82*G82%) -> 0 | P82: Insurer's Liability
C83: paint materail after dep | E83: =(E81-E82) -> 0 | F83: =F80 -> 9 | G83: =G80 -> 9 | H83: 0 | I83: =(E83*H83) -> 0 | J83: =E83+(E83*F83%)+(E83*G83%) -> 0 | P83: Net Liability | S83: =(J78+J80+J83+E84)-(E86)-(E85) -> -1000
C84: Towing Charge | E84: 0 | P84: Dep Reimbursment | S84: =IF(P84=AA23,0,IF(P84=AA24,S75+S76)) -> 0
C85: Less :Volauntry Excess | P85: Consumabels | S85: =IF(P85=AA25,0,IF(P85=AA26,J77)) -> 0
C86: Less;Compulsary Excess | E86: =IF(H26<=1500,1000,2000) -> 1000 | P86: Total Insurer's Share With add on coverage | S86: =SUM(S83:S85) -> -1000
R87: For office use only
Q88: labour | S88: =J80+E84 -> 0
Q89: Paint | S89: =J83 -> 0
Q90: Parts | S90: =J78-E86 -> -1000
C91: Additional Remarks: | F91: Payment To | H91: 0 | Q91: Dep. Coverage | S91: =S84-E85 -> 0
Q92: Consumables Coverage | S92: =S85 -> 0
R93: Total | S93: =S88+S89+S90+S91+S92 -> -1000
C94: Claim Processed by: | F94: ALL METAL PARTS | H94: =SUMIF(E44:E69,"Metal",J44:J69) -> 0 | I94: =COUNTIF(E44:E69,"Metal") -> 0 | J94: Claim Approved by
F95: ALL GLSS PARTS | H95: =SUMIF(E44:E69,"Glass",J44:J69) -> 0 | I95: =COUNTIF(E44:E69,"Glass") -> 0
C96: Signature with Date: | F96: ALLPLASTIC PARTS | H96: =SUMIF(E44:E69,"Plastic/Rubber",J44:J69) -> 0 | I96: =COUNTIF(E44:E69,"Plastic/Rubber") -> 0
F97: ALL CONS PARTS | H97: =SUMIF(E44:E69,"Consumable",J44:J69) -> 0 | I97: =COUNTIF(E44:E69,"Consumables") -> 0
E102: Tax | F102: =+SUM(K44:L69) -> 0 | P102: =854444-852837 -> 1607 | R102: 843960.1 | S102: 852444.57
E103: Original RC and DL | G103: YES | R103: 1000 | S103: 2000
E104: UR and RI | G104: YES | R104: 1445.02
E105: Damage Parts Photo | G105: YES | R105: =517.19+6935.5 -> 7452.69
E106: Excess Clause | G106: YES | R106: =+R105*28% -> 2086.7532
E107: Without Paint Change | G107: YES
C112: S.No | D112: Repair/ Replace | E112: Description | J112: Parts@list (A) | O112: Depn (B) in % | P112: Net (A-B) | Q112: Labour Remove Refit | R112: Labour Repair | S112: Paint
E113: Material | G113: Side | H113: Section | I113: Part
E114: Metal
J115: =DSUM(C41:S69,J41,C112:S114) -> #VALUE! | P115: =DSUM(C41:S69,P41,C112:S114) -> #VALUE!
C119: S.No | D119: Repair/ Replace | E119: Description | J119: Parts@list (A) | O119: Depn (B) in % | P119: Net (A-B) | Q119: Labour Remove Refit | R119: Labour Repair | S119: Paint
E120: Material | G120: Side | H120: Section | I120: Part
E121: Glass
J122: =DSUM(C41:S49,J41,C119:S121) -> #VALUE! | P122: =DSUM(E41:T49,P41,E119:T121) -> #VALUE!
C126: S.No | D126: Repair/ Replace | E126: Description | J126: Parts@list (A) | O126: Depn (B) in % | P126: Net (A-B) | Q126: Labour Remove Refit | R126: Labour Repair | S126: Paint
...

Sheet Survey Report 
A1: MOHD.YAMIN | F1: 208-B , Rishabh corporate tower ,
A2: Surveyor & Loss Assessor | F2: Karkardooma community centre,Delhi
A3: Lic No.72970,Valid upto 23/08/2026 | F3: Mobile:+91-9818430881
A5: MOTOR SURVEY REPORT [FINAL]
A7: Claim No | B7: ='Repair Assessment Sheet'!Q13 -> 0 | D7: Report Ref No. | E7: Tata- | F7: Date | G7: ='Repair Assessment Sheet'!R10 -> 0
A8: Policy No. | B8: ='Repair Assessment Sheet'!E17 -> 0 | D8: Period : | E8: ='Repair Assessment Sheet'!E18:G18 -> 0 | F8: TO | G8: ='Repair Assessment Sheet'!H18 -> 0
A10: Insured | B10: ='Repair Assessment Sheet'!D13 -> 0
A11: Address
C13: As per RC | F13: As per Insurance
A14: Registration No | C14: ='Repair Assessment Sheet'!E22 -> 0 | F14: =C14 -> 0
A15: Chassis No. | C15: ='Repair Assessment Sheet'!H24 -> 0 | F15: =C15 -> 0
A16: Engine No. | C16: ='Repair Assessment Sheet'!H25 -> 0 | F16: =C16 -> 0
A18: Vehicle Particulars | E18: RC | F18: Verified
A19: Registration No | C19: =C14 -> 0 | E19: Cubic Capacity | G19: ='Repair Assessment Sheet'!H26 -> 0
A20: Chassis No | C20: =C15 -> 0 | E20: Make/Model | G20: ='Repair Assessment Sheet'!E25 -> 0
A21: Engine No | C21: =C16 -> 0 | E21: Date Of Registration | G21: ='Repair Assessment Sheet'!E26 -> 0
A22: Odometer Reading | C22: ='Repair Assessment Sheet'!E23 -> 0 | E22: Color | G22: ='Repair Assessment Sheet'!E27 -> 0
A24: Driving Particulars | E24: DL | F24: Verified
A25: Name | C25: ='Repair Assessment Sheet'!P22 -> 0
A26: Driving Licence No. | C26: ='Repair Assessment Sheet'!P23 -> 0
A27: Issue Date
A28: Expiring On | C28: ='Repair Assessment Sheet'!P24 -> 0
A29: Valid For | C29: ='Repair Assessment Sheet'!S24 -> 0
A30: Issuing Authority | C30: ='Repair Assessment Sheet'!S23 -> 0
A32: Accident Particulars
A33: Date of Accident | D33: ='Repair Assessment Sheet'!Q16 -> 0
A34: Place of Accident & Time | D34: ='Repair Assessment Sheet'!Q14 -> 0
A35: Place of Survey | D35: ='Repair Assessment Sheet'!Q15 -> 0
A36: Date of Survey | C36: ='Repair Assessment Sheet'!E10 -> 0 | E36: Date of Re-inspection
A38: Details of Accident & Comments
A39: As per Claimform,
A42: Police Report | D42: No,as per Claimform.
A43: Injuries to Driver/Passengers/Third Parties or Damage to properties of Third Party. | D43: No,as per Claimform.
A52: Remarks :
A53: 1
A54: 2
A56: This Report is issued without prejudice subject to the terms & conditions of the Insurance Policy.
G59: MOHD.YAMIN
A60: MOHD.YAMIN | F60: 208-B , Rishabh corporate tower ,
A61: Surveyor & Loss Assessor | F61: Karkardooma community centre,Delhi
A62: Lic No.72970,Valid upto 23/08/2026 | F62: Mobile:+91-9818430881
A67: Claim No | B67: =B7 -> 0 | D67: Report Ref No. | E67: =E7 -> Tata- | F67: Date | G67: =G7 -> 0
A68: Policy No. | B68: =+B8 -> 0 | D68: Period : | E68: =E8 -> 0 | F68: TO | G68: =G8 -> 0
A70: Insurer
A72: Insured | B72: =B12 -> 0
A74: Registration No. | C74: =C14 -> 0
D78: SURVEY FEE BILL
A80: S.No. | B80: Particulars | E80: Amount | L80: Fee | M80: Conveyance | O80: Total
A82: 1 | B82: Survey Fee Final | E82: 2700 | K82: 0-15 | L82: 1200 | M82: 300 | O82: =+L82+M82 -> 1500
K84: 15-50 | L84: 2200 | M84: 300 | O84: =+L84+M84 -> 2500
A86: 2 | B86: Conveyance Final | E86: 300 | K86: 50-1 lakh | L86: 2700 | M86: 300 | O86: =+L86+M86 -> 3000
K88: 1 - 3 lakh | L88: 3200 | M88: 300 | O88: =+L88+M88 -> 3500
A90: 3 | B90: Photo Charges Final | E90: 0 | K90: above 3 lakh | M90: 3200 +0.70% over 3 lakh
D92: Total | E92: =+SUM(E82:E91) -> 3000
E93: 0
E94: =+E92+E93 -> 3000
B97: A/C No. 50200045633320 | K97: 3200
B98: HDFC BANK , KRISHNA NAGAR | K98: =550000*0.7% -> 3850
B99: IFSC : HDFC0000709
F100: [ MOHD. YAMIN ]
F101: SURVEYOR

Sheet ICan Upload 
A1: Preliminary Details | XER1: Yes | XET1: Remove/Install | XEV1: Plastic/Rubber | XEW1: NA | XEX1: Front | XEY1: 0 | XEZ1: Invoice 1
XER2: No | XET2: Replace | XEV2: Metal | XEW2: Left | XEX2: Center | XEY2: 5 | XEZ2: Invoice 2
A3: Date of Vehicle Registration | D3: Invoice No. 1 | G3: Invoice 1 Date | J3: Invoice amount 1 | M3: Paint | O3: Labour | T3: Metal | U3: =COUNTIF(D14:D300,"Metal") -> 0 | XET3: Repair | XEV3: Glass | XEW3: Right | XEX3: Rear | XEY3: 12 | XEZ3: Invoice 3
A4: Paint Bifurcation Available | B4: No | D4: Invoice No. 2 | G4: Invoice 2 Date | J4: Invoice amount 2 | M4: Sac Tax | N4: Sac Code | O4: Sac Tax | P4: Sac Code | T4: Plastic | U4: =COUNTIF(D14:D300,"Plastic/Rubber") -> 0 | XEV4: Fiber Glass | XEY4: 18
A5: Is Invoice Raised in favour of Tata AIG | B5: Yes | D5: Invoice No. 3 | G5: Invoice 3 Date | J5: Invoice amount 3 | M5: 18 | N5: 998729 | O5: 18 | P5: 998729 | T5: Consumable | U5: =COUNTIF(D14:D300,"Consumables") -> 0 | XEV5: Consumables | XEY5: 28
T6: Glass | U6: =COUNTIF(D14:D300,"Glass") -> 0 | XEV6: Engine Secure
XEV7: Tyre Secure
XEV8: Key Replacement
A12: Repair Assessment Sheet | T12: Tax | U12: =SUM(L14:L300) -> 0
A13: S. No | B13: Invoice No | C13: Repair Replace | D13: Material | E13: Side | F13: Section | G13: Part | J13: HSN/SAC Code | K13: Part Price | L13: Tax % | M13: R & I Labour | N13: Repair Labour | O13: Paint Labour | P13: Paint Material
A14: 1 | G14: ='Repair Assessment Sheet'!H44 -> 0 | K14: ='Repair Assessment Sheet'!J44 -> 0 | M14: ='Repair Assessment Sheet'!Q44 -> 0 | N14: ='Repair Assessment Sheet'!R44 -> 0 | O14: ='Repair Assessment Sheet'!S44 -> 0 | R14: ='Repair Assessment Sheet'!V44 -> 0.28
A15: 2 | G15: ='Repair Assessment Sheet'!H45 -> 0 | K15: ='Repair Assessment Sheet'!J45 -> 0 | M15: ='Repair Assessment Sheet'!Q45 -> 0 | N15: ='Repair Assessment Sheet'!R45 -> 0 | O15: ='Repair Assessment Sheet'!S45 -> 0 | R15: ='Repair Assessment Sheet'!V45 -> 0.18
A16: 3 | G16: ='Repair Assessment Sheet'!H46 -> 0 | K16: ='Repair Assessment Sheet'!J46 -> 0 | M16: ='Repair Assessment Sheet'!Q46 -> 0 | N16: ='Repair Assessment Sheet'!R46 -> 0 | O16: ='Repair Assessment Sheet'!S46 -> 0 | R16: ='Repair Assessment Sheet'!V46 -> 0.28
A17: 4 | G17: ='Repair Assessment Sheet'!H47 -> 0 | K17: ='Repair Assessment Sheet'!J47 -> 0 | M17: ='Repair Assessment Sheet'!Q47 -> 0 | N17: ='Repair Assessment Sheet'!R47 -> 0 | O17: ='Repair Assessment Sheet'!S47 -> 0 | R17: ='Repair Assessment Sheet'!V47 -> 0.18
A18: 5 | G18: ='Repair Assessment Sheet'!H48 -> 0 | K18: ='Repair Assessment Sheet'!J48 -> 0 | M18: ='Repair Assessment Sheet'!Q48 -> 0 | N18: ='Repair Assessment Sheet'!R48 -> 0 | O18: ='Repair Assessment Sheet'!S48 -> 0 | R18: ='Repair Assessment Sheet'!V48 -> 0.18
A19: 6 | G19: ='Repair Assessment Sheet'!H49 -> 0 | K19: ='Repair Assessment Sheet'!J49 -> 0 | M19: ='Repair Assessment Sheet'!Q49 -> 0 | N19: ='Repair Assessment Sheet'!R49 -> 0 | O19: ='Repair Assessment Sheet'!S49 -> 0 | R19: ='Repair Assessment Sheet'!V49 -> 0.18
A20: 7 | G20: ='Repair Assessment Sheet'!H50 -> 0 | K20: ='Repair Assessment Sheet'!J50 -> 0 | M20: ='Repair Assessment Sheet'!Q50 -> 0 | N20: ='Repair Assessment Sheet'!R50 -> 0 | O20: ='Repair Assessment Sheet'!S50 -> 0 | R20: ='Repair Assessment Sheet'!V50 -> 0.18
A21: 8 | G21: ='Repair Assessment Sheet'!H51 -> 0 | K21: ='Repair Assessment Sheet'!J51 -> 0 | M21: ='Repair Assessment Sheet'!Q51 -> 0 | N21: ='Repair Assessment Sheet'!R51 -> 0 | O21: ='Repair Assessment Sheet'!S51 -> 0 | R21: ='Repair Assessment Sheet'!V51 -> 0.18
A22: 9 | G22: ='Repair Assessment Sheet'!H52 -> 0 | K22: ='Repair Assessment Sheet'!J52 -> 0 | M22: ='Repair Assessment Sheet'!Q52 -> 0 | N22: ='Repair Assessment Sheet'!R52 -> 0 | O22: ='Repair Assessment Sheet'!S52 -> 0 | R22: ='Repair Assessment Sheet'!V52 -> 0.18
A23: 10 | G23: ='Repair Assessment Sheet'!H53 -> 0 | K23: ='Repair Assessment Sheet'!J53 -> 0 | M23: ='Repair Assessment Sheet'!Q53 -> 0 | N23: ='Repair Assessment Sheet'!R53 -> 0 | O23: ='Repair Assessment Sheet'!S53 -> 0 | R23: ='Repair Assessment Sheet'!V53 -> 0.28
A24: 11 | G24: ='Repair Assessment Sheet'!H54 -> 0 | K24: ='Repair Assessment Sheet'!J54 -> 0 | M24: ='Repair Assessment Sheet'!Q54 -> 0 | N24: ='Repair Assessment Sheet'!R54 -> 0 | O24: ='Repair Assessment Sheet'!S54 -> 0 | R24: ='Repair Assessment Sheet'!V54 -> 0.18
A25: 12 | G25: ='Repair Assessment Sheet'!H55 -> 0 | K25: ='Repair Assessment Sheet'!J55 -> 0 | M25: ='Repair Assessment Sheet'!Q55 -> 0 | N25: ='Repair Assessment Sheet'!R55 -> 0 | O25: ='Repair Assessment Sheet'!S55 -> 0 | R25: ='Repair Assessment Sheet'!V55 -> 0.28
A26: 13 | G26: ='Repair Assessment Sheet'!#REF! -> #REF! | K26: ='Repair Assessment Sheet'!#REF! -> #REF! | M26: ='Repair Assessment Sheet'!#REF! -> #REF! | N26: ='Repair Assessment Sheet'!#REF! -> #REF! | O26: ='Repair Assessment Sheet'!#REF! -> #REF! | R26: ='Repair Assessment Sheet'!#REF! -> #REF!
A27: 14 | G27: ='Repair Assessment Sheet'!H56 -> 0 | K27: ='Repair Assessment Sheet'!J56 -> 0 | M27: ='Repair Assessment Sheet'!Q56 -> 0 | N27: ='Repair Assessment Sheet'!R56 -> 0 | O27: ='Repair Assessment Sheet'!S56 -> 0 | R27: ='Repair Assessment Sheet'!V56 -> 0.28
A28: 15 | G28: ='Repair Assessment Sheet'!H57 -> 0 | K28: ='Repair Assessment Sheet'!J57 -> 0 | M28: ='Repair Assessment Sheet'!Q57 -> 0 | N28: ='Repair Assessment Sheet'!R57 -> 0 | O28: ='Repair Assessment Sheet'!S57 -> 0 | R28: ='Repair Assessment Sheet'!V57 -> 0.18
A29: 16 | G29: ='Repair Assessment Sheet'!H58 -> 0 | K29: ='Repair Assessment Sheet'!J58 -> 0 | M29: ='Repair Assessment Sheet'!Q58 -> 0 | N29: ='Repair Assessment Sheet'!R58 -> 0 | O29: ='Repair Assessment Sheet'!S58 -> 0 | R29: ='Repair Assessment Sheet'!V58 -> 0.28
A30: 17 | G30: ='Repair Assessment Sheet'!H59 -> 0 | K30: ='Repair Assessment Sheet'!J59 -> 0 | M30: ='Repair Assessment Sheet'!Q59 -> 0 | N30: ='Repair Assessment Sheet'!R59 -> 0 | O30: ='Repair Assessment Sheet'!S59 -> 0 | R30: ='Repair Assessment Sheet'!V59 -> 0.28
A31: 18 | G31: ='Repair Assessment Sheet'!H60 -> 0 | K31: ='Repair Assessment Sheet'!J60 -> 0 | M31: ='Repair Assessment Sheet'!Q60 -> 0 | N31: ='Repair Assessment Sheet'!R60 -> 0 | O31: ='Repair Assessment Sheet'!S60 -> 0 | R31: ='Repair Assessment Sheet'!V60 -> 0.28
A32: 19 | G32: ='Repair Assessment Sheet'!H61 -> 0 | K32: ='Repair Assessment Sheet'!J61 -> 0 | M32: ='Repair Assessment Sheet'!Q61 -> 0 | N32: ='Repair Assessment Sheet'!R61 -> 0 | O32: ='Repair Assessment Sheet'!S61 -> 0 | R32: ='Repair Assessment Sheet'!V61 -> 0.18
A33: 20 | G33: ='Repair Assessment Sheet'!H62 -> 0 | K33: ='Repair Assessment Sheet'!J62 -> 0 | M33: ='Repair Assessment Sheet'!Q62 -> 0 | N33: ='Repair Assessment Sheet'!R62 -> 0 | O33: ='Repair Assessment Sheet'!S62 -> 0 | R33: ='Repair Assessment Sheet'!V62 -> 0.18
A34: 21 | G34: ='Repair Assessment Sheet'!H63 -> 0 | K34: ='Repair Assessment Sheet'!J63 -> 0 | M34: ='Repair Assessment Sheet'!Q63 -> 0 | N34: ='Repair Assessment Sheet'!R63 -> 0 | O34: ='Repair Assessment Sheet'!S63 -> 0 | R34: ='Repair Assessment Sheet'!V63 -> 0.28
A35: 22 | G35: ='Repair Assessment Sheet'!H64 -> 0 | K35: ='Repair Assessment Sheet'!J64 -> 0 | M35: ='Repair Assessment Sheet'!Q64 -> 0 | N35: ='Repair Assessment Sheet'!R64 -> 0 | O35: ='Repair Assessment Sheet'!S64 -> 0 | R35: ='Repair Assessment Sheet'!V64 -> 0.28
A36: 23 | G36: ='Repair Assessment Sheet'!H65 -> 0 | K36: ='Repair Assessment Sheet'!J65 -> 0 | M36: ='Repair Assessment Sheet'!Q65 -> 0 | N36: ='Repair Assessment Sheet'!R65 -> 0 | O36: ='Repair Assessment Sheet'!S65 -> 0 | R36: ='Repair Assessment Sheet'!V65 -> 0.28
A37: 24 | G37: ='Repair Assessment Sheet'!H66 -> 0 | K37: ='Repair Assessment Sheet'!J66 -> 0 | M37: ='Repair Assessment Sheet'!Q66 -> 0 | N37: ='Repair Assessment Sheet'!R66 -> 0 | O37: ='Repair Assessment Sheet'!S66 -> 0 | R37: ='Repair Assessment Sheet'!V66 -> 0.18
A38: 25 | G38: ='Repair Assessment Sheet'!H67 -> 0 | K38: ='Repair Assessment Sheet'!J67 -> 0 | M38: ='Repair Assessment Sheet'!Q67 -> 0 | N38: ='Repair Assessment Sheet'!R67 -> 0 | O38: ='Repair Assessment Sheet'!S67 -> 0 | R38: ='Repair Assessment Sheet'!V67 -> 0.18
A39: 26 | G39: ='Repair Assessment Sheet'!#REF! -> #REF! | K39: ='Repair Assessment Sheet'!#REF! -> #REF! | M39: ='Repair Assessment Sheet'!#REF! -> #REF! | N39: ='Repair Assessment Sheet'!#REF! -> #REF! | O39: ='Repair Assessment Sheet'!#REF! -> #REF! | R39: ='Repair Assessment Sheet'!#REF! -> #REF!
A40: 27 | G40: ='Repair Assessment Sheet'!#REF! -> #REF! | K40: ='Repair Assessment Sheet'!#REF! -> #REF! | M40: ='Repair Assessment Sheet'!#REF! -> #REF! | N40: ='Repair Assessment Sheet'!#REF! -> #REF! | O40: ='Repair Assessment Sheet'!#REF! -> #REF! | R40: ='Repair Assessment Sheet'!#REF! -> #REF!
A41: 28 | G41: ='Repair Assessment Sheet'!#REF! -> #REF! | K41: ='Repair Assessment Sheet'!#REF! -> #REF! | M41: ='Repair Assessment Sheet'!#REF! -> #REF! | N41: ='Repair Assessment Sheet'!#REF! -> #REF! | O41: ='Repair Assessment Sheet'!#REF! -> #REF! | R41: ='Repair Assessment Sheet'!#REF! -> #REF!
A42: 29 | G42: ='Repair Assessment Sheet'!#REF! -> #REF! | K42: ='Repair Assessment Sheet'!#REF! -> #REF! | M42: ='Repair Assessment Sheet'!#REF! -> #REF! | N42: ='Repair Assessment Sheet'!#REF! -> #REF! | O42: ='Repair Assessment Sheet'!#REF! -> #REF! | R42: ='Repair Assessment Sheet'!#REF! -> #REF!
A43: 30 | G43: ='Repair Assessment Sheet'!#REF! -> #REF! | K43: ='Repair Assessment Sheet'!#REF! -> #REF! | M43: ='Repair Assessment Sheet'!#REF! -> #REF! | N43: ='Repair Assessment Sheet'!#REF! -> #REF! | O43: ='Repair Assessment Sheet'!#REF! -> #REF! | R43: ='Repair Assessment Sheet'!#REF! -> #REF!
A44: 31 | G44: ='Repair Assessment Sheet'!#REF! -> #REF! | K44: ='Repair Assessment Sheet'!#REF! -> #REF! | M44: ='Repair Assessment Sheet'!#REF! -> #REF! | N44: ='Repair Assessment Sheet'!#REF! -> #REF! | O44: ='Repair Assessment Sheet'!#REF! -> #REF! | R44: ='Repair Assessment Sheet'!#REF! -> #REF!
A45: 32 | G45: ='Repair Assessment Sheet'!#REF! -> #REF! | K45: ='Repair Assessment Sheet'!#REF! -> #REF! | M45: ='Repair Assessment Sheet'!#REF! -> #REF! | N45: ='Repair Assessment Sheet'!#REF! -> #REF! | O45: ='Repair Assessment Sheet'!#REF! -> #REF! | R45: ='Repair Assessment Sheet'!#REF! -> #REF!
A46: 33 | G46: ='Repair Assessment Sheet'!#REF! -> #REF! | K46: ='Repair Assessment Sheet'!#REF! -> #REF! | M46: ='Repair Assessment Sheet'!#REF! -> #REF! | N46: ='Repair Assessment Sheet'!#REF! -> #REF! | O46: ='Repair Assessment Sheet'!#REF! -> #REF! | R46: ='Repair Assessment Sheet'!#REF! -> #REF!
A47: 34 | G47: ='Repair Assessment Sheet'!#REF! -> #REF! | K47: ='Repair Assessment Sheet'!#REF! -> #REF! | M47: ='Repair Assessment Sheet'!#REF! -> #REF! | N47: ='Repair Assessment Sheet'!#REF! -> #REF! | O47: ='Repair Assessment Sheet'!#REF! -> #REF! | R47: ='Repair Assessment Sheet'!#REF! -> #REF!
A48: 35 | G48: ='Repair Assessment Sheet'!#REF! -> #REF! | K48: ='Repair Assessment Sheet'!#REF! -> #REF! | M48: ='Repair Assessment Sheet'!#REF! -> #REF! | N48: ='Repair Assessment Sheet'!#REF! -> #REF! | O48: ='Repair Assessment Sheet'!#REF! -> #REF! | R48: ='Repair Assessment Sheet'!#REF! -> #REF!
A49: 36 | G49: ='Repair Assessment Sheet'!#REF! -> #REF! | K49: ='Repair Assessment Sheet'!#REF! -> #REF! | M49: ='Repair Assessment Sheet'!#REF! -> #REF! | N49: ='Repair Assessment Sheet'!#REF! -> #REF! | O49: ='Repair Assessment Sheet'!#REF! -> #REF! | R49: ='Repair Assessment Sheet'!#REF! -> #REF!
A50: 37 | G50: ='Repair Assessment Sheet'!#REF! -> #REF! | K50: ='Repair Assessment Sheet'!#REF! -> #REF! | M50: ='Repair Assessment Sheet'!#REF! -> #REF! | N50: ='Repair Assessment Sheet'!#REF! -> #REF! | O50: ='Repair Assessment Sheet'!#REF! -> #REF! | R50: ='Repair Assessment Sheet'!#REF! -> #REF!
... A264: 251 | G264: ='Repair Assessment Sheet'!#REF! -> #REF! | K264: ='Repair Assessment Sheet'!#REF! -> #REF! | M264: ='Repair Assessment Sheet'!#REF! -> #REF! | N264: ='Repair Assessment Sheet'!#REF! -> #REF! | O264: ='Repair Assessment Sheet'!#REF! -> #REF! | R264: ='Repair Assessment Sheet'!#REF! -> #REF!
A265: 252 | G265: ='Repair Assessment Sheet'!H68 -> 0 | K265: ='Repair Assessment Sheet'!J68 -> 0 | M265: ='Repair Assessment Sheet'!Q68 -> 0 | N265: ='Repair Assessment Sheet'!R68 -> 0 | O265: ='Repair Assessment Sheet'!S68 -> 0
A266: 253 | G266: ='Repair Assessment Sheet'!H69 -> 0 | K266: ='Repair Assessment Sheet'!J69 -> 0 | M266: ='Repair Assessment Sheet'!Q69 -> 0 | N266: ='Repair Assessment Sheet'!R69 -> 0 | O266: ='Repair Assessment Sheet'!S69 -> 0
A267: 254 | G267: ='Repair Assessment Sheet'!H70 -> 0 | K267: ='Repair Assessment Sheet'!J70 -> 0 | M267: ='Repair Assessment Sheet'!Q70 -> 0 | N267: ='Repair Assessment Sheet'!R70 -> 0 | O267: ='Repair Assessment Sheet'!S70 -> 0
A268: 255 | G268: ='Repair Assessment Sheet'!H71 -> 0 | K268: ='Repair Assessment Sheet'!J71 -> 0
A269: 256 | G269: ='Repair Assessment Sheet'!H72 -> 0
A270: 257 | G270: ='Repair Assessment Sheet'!H73 -> 0
A271: 258 | G271: ='Repair Assessment Sheet'!H74 -> Discount
A272: 259 | G272: ='Repair Assessment Sheet'!H75 -> 0
A273: 260 | G273: ='Repair Assessment Sheet'!H76 -> 0
A274: 261 | G274: ='Repair Assessment Sheet'!H77 -> 0
A275: 262 | G275: ='Repair Assessment Sheet'!H78 -> 0
A276: 263 | G276: ='Repair Assessment Sheet'!H79 -> 0
A277: 264
A278: 265
A279: 266
A280: 267
A281: 268
A282: 269
A283: 270
A284: 271
A285: 272
A286: 273
A287: 274
A288: 275
... A513: 500

Sheet ICan Upload  (2)
A1: Preliminary Details | XER1: Yes | XET1: Remove/Install | XEV1: Plastic/Rubber | XEW1: NA | XEX1: Front | XEY1: 0 | XEZ1: Invoice 1
XER2: No | XET2: Replace | XEV2: Metal | XEW2: Left | XEX2: Center | XEY2: 5 | XEZ2: Invoice 2
A3: Date of Vehicle Registration | B3: ='Repair Assessment Sheet'!E26 -> 0 | D3: Invoice No. 1 | E3: 87498574 | G3: Invoice 1 Date | J3: Invoice amount 1 | M3: Paint | O3: Labour | T3: Metal | U3: =COUNTIF(D14:D73,"Metal") -> 0 | XET3: Repair | XEV3: Glass | XEW3: Right | XEX3: Rear | XEY3: 12 | XEZ3: Invoice 3
A4: Paint Bifurcation Available | B4: No | D4: Invoice No. 2 | G4: Invoice 2 Date | J4: Invoice amount 2 | M4: Sac Tax | N4: Sac Code | O4: Sac Tax | P4: Sac Code | T4: Plastic | U4: =COUNTIF(D14:D73,"Plastic/Rubber") -> 0 | XEV4: Fiber Glass | XEY4: 18
A5: Is Invoice Raised in favour of Tata AIG | B5: Yes | D5: Invoice No. 3 | G5: Invoice 3 Date | J5: Invoice amount 3 | M5: 18 | N5: 998729 | O5: 18 | P5: 998729 | T5: Consumable | U5: =COUNTIF(D14:D73,"Consumables") -> 0 | XEV5: Consumables | XEY5: 28
T6: Glass | U6: =COUNTIF(D14:D73,"Glass") -> 0 | XEV6: Engine Secure
XEV7: Tyre Secure
XEV8: Key Replacement
A12: Repair Assessment Sheet | T12: Tax | U12: =SUM(L14:L73) -> #REF!
A13: S. No | B13: Invoice No | C13: Repair Replace | D13: Material | E13: Side | F13: Section | G13: Part | J13: HSN/SAC Code | K13: Part Price | L13: Tax % | M13: R & I Labour | N13: Repair Labour | O13: Paint Labour | P13: Paint Material
A14: 1 | B14: =$E$3 -> 87498574 | C14: ='Repair Assessment Sheet'!D44 -> 0 | D14: ='Repair Assessment Sheet'!E44 -> 0 | E14: ='Repair Assessment Sheet'!F44 -> 0 | F14: ='Repair Assessment Sheet'!G44 -> 0 | G14: ='Repair Assessment Sheet'!H44 -> 0 | J14: ='Repair Assessment Sheet'!T44 -> 85072000 | K14: ='Repair Assessment Sheet'!J44 -> 0 | L14: ='Repair Assessment Sheet'!K44*200 -> 0 | M14: ='Repair Assessment Sheet'!Q44 -> 0 | N14: ='Repair Assessment Sheet'!R44 -> 0 | O14: ='Repair Assessment Sheet'!S44 -> 0
A15: 2 | B15: =$E$3 -> 87498574 | C15: ='Repair Assessment Sheet'!D45 -> 0 | D15: ='Repair Assessment Sheet'!E45 -> 0 | E15: ='Repair Assessment Sheet'!F45 -> 0 | F15: ='Repair Assessment Sheet'!G45 -> 0 | G15: ='Repair Assessment Sheet'!H45 -> 0 | J15: ='Repair Assessment Sheet'!T45 -> 85443000 | K15: ='Repair Assessment Sheet'!J45 -> 0 | L15: ='Repair Assessment Sheet'!K45*200 -> 0 | M15: ='Repair Assessment Sheet'!Q45 -> 0 | N15: ='Repair Assessment Sheet'!R45 -> 0 | O15: ='Repair Assessment Sheet'!S45 -> 0
A16: 3 | B16: =$E$3 -> 87498574 | C16: ='Repair Assessment Sheet'!D46 -> 0 | D16: ='Repair Assessment Sheet'!E46 -> 0 | E16: ='Repair Assessment Sheet'!F46 -> 0 | F16: ='Repair Assessment Sheet'!G46 -> 0 | G16: ='Repair Assessment Sheet'!H46 -> 0 | J16: ='Repair Assessment Sheet'!T46 -> 87089900 | K16: ='Repair Assessment Sheet'!J46 -> 0 | L16: ='Repair Assessment Sheet'!K46*200 -> 0 | M16: ='Repair Assessment Sheet'!Q46 -> 0 | N16: ='Repair Assessment Sheet'!R46 -> 0 | O16: ='Repair Assessment Sheet'!S46 -> 0
A17: 4 | B17: =$E$3 -> 87498574 | C17: ='Repair Assessment Sheet'!D47 -> 0 | D17: ='Repair Assessment Sheet'!E47 -> 0 | E17: ='Repair Assessment Sheet'!F47 -> 0 | F17: ='Repair Assessment Sheet'!G47 -> 0 | G17: ='Repair Assessment Sheet'!H47 -> 0 | J17: ='Repair Assessment Sheet'!T47 -> 40169340 | K17: ='Repair Assessment Sheet'!J47 -> 0 | L17: ='Repair Assessment Sheet'!K47*200 -> 0 | M17: ='Repair Assessment Sheet'!Q47 -> 0 | N17: ='Repair Assessment Sheet'!R47 -> 0 | O17: ='Repair Assessment Sheet'!S47 -> 0
A18: 5 | B18: =$E$3 -> 87498574 | C18: ='Repair Assessment Sheet'!D48 -> 0 | D18: ='Repair Assessment Sheet'!E48 -> 0 | E18: ='Repair Assessment Sheet'!F48 -> 0 | F18: ='Repair Assessment Sheet'!G48 -> 0 | G18: ='Repair Assessment Sheet'!H48 -> 0 | J18: ='Repair Assessment Sheet'!T48 -> 40169340 | K18: ='Repair Assessment Sheet'!J48 -> 0 | L18: ='Repair Assessment Sheet'!K48*200 -> 0 | M18: ='Repair Assessment Sheet'!Q48 -> 0 | N18: ='Repair Assessment Sheet'!R48 -> 0 | O18: ='Repair Assessment Sheet'!S48 -> 0
A19: 6 | B19: =$E$3 -> 87498574 | C19: ='Repair Assessment Sheet'!D49 -> 0 | D19: ='Repair Assessment Sheet'!E49 -> 0 | E19: ='Repair Assessment Sheet'!F49 -> 0 | F19: ='Repair Assessment Sheet'!G49 -> 0 | G19: ='Repair Assessment Sheet'!H49 -> 0 | J19: ='Repair Assessment Sheet'!T49 -> 40094200 | K19: ='Repair Assessment Sheet'!J49 -> 0 | L19: ='Repair Assessment Sheet'!K49*200 -> 0 | M19: ='Repair Assessment Sheet'!Q49 -> 0 | N19: ='Repair Assessment Sheet'!R49 -> 0 | O19: ='Repair Assessment Sheet'!S49 -> 0
A20: 7 | B20: =$E$3 -> 87498574 | C20: ='Repair Assessment Sheet'!D50 -> 0 | D20: ='Repair Assessment Sheet'!E50 -> 0 | E20: ='Repair Assessment Sheet'!F50 -> 0 | F20: ='Repair Assessment Sheet'!G50 -> 0 | G20: ='Repair Assessment Sheet'!H50 -> 0 | J20: ='Repair Assessment Sheet'!T50 -> 40094200 | K20: ='Repair Assessment Sheet'!J50 -> 0 | L20: ='Repair Assessment Sheet'!K50*200 -> 0 | M20: ='Repair Assessment Sheet'!Q50 -> 0 | N20: ='Repair Assessment Sheet'!R50 -> 0 | O20: ='Repair Assessment Sheet'!S50 -> 0
A21: 8 | B21: =$E$3 -> 87498574 | C21: ='Repair Assessment Sheet'!D51 -> 0 | D21: ='Repair Assessment Sheet'!E51 -> 0 | E21: ='Repair Assessment Sheet'!F51 -> 0 | F21: ='Repair Assessment Sheet'!G51 -> 0 | G21: ='Repair Assessment Sheet'!H51 -> 0 | J21: ='Repair Assessment Sheet'!T51 -> 84213100 | K21: ='Repair Assessment Sheet'!J51 -> 0 | L21: ='Repair Assessment Sheet'!K51*200 -> 0 | M21: ='Repair Assessment Sheet'!Q51 -> 0 | N21: ='Repair Assessment Sheet'!R51 -> 0 | O21: ='Repair Assessment Sheet'!S51 -> 0
A22: 9 | B22: =$E$3 -> 87498574 | C22: ='Repair Assessment Sheet'!D52 -> 0 | D22: ='Repair Assessment Sheet'!E52 -> 0 | E22: ='Repair Assessment Sheet'!F52 -> 0 | F22: ='Repair Assessment Sheet'!G52 -> 0 | G22: ='Repair Assessment Sheet'!H52 -> 0 | J22: ='Repair Assessment Sheet'!T52 -> 40094200 | K22: ='Repair Assessment Sheet'!J52 -> 0 | L22: ='Repair Assessment Sheet'!K52*200 -> 0 | M22: ='Repair Assessment Sheet'!Q52 -> 0 | N22: ='Repair Assessment Sheet'!R52 -> 0 | O22: ='Repair Assessment Sheet'!S52 -> 0
A23: 10 | B23: =$E$3 -> 87498574 | C23: ='Repair Assessment Sheet'!D53 -> 0 | D23: ='Repair Assessment Sheet'!E53 -> 0 | E23: ='Repair Assessment Sheet'!F53 -> 0 | F23: ='Repair Assessment Sheet'!G53 -> 0 | G23: ='Repair Assessment Sheet'!H53 -> 0 | J23: ='Repair Assessment Sheet'!T53 -> 84099990 | K23: ='Repair Assessment Sheet'!J53 -> 0 | L23: ='Repair Assessment Sheet'!K53*200 -> 0 | M23: ='Repair Assessment Sheet'!Q53 -> 0 | N23: ='Repair Assessment Sheet'!R53 -> 0 | O23: ='Repair Assessment Sheet'!S53 -> 0
A24: 11 | B24: =$E$3 -> 87498574 | C24: ='Repair Assessment Sheet'!D54 -> 0 | D24: ='Repair Assessment Sheet'!E54 -> 0 | E24: ='Repair Assessment Sheet'!F54 -> 0 | F24: ='Repair Assessment Sheet'!G54 -> 0 | G24: ='Repair Assessment Sheet'!H54 -> 0 | J24: ='Repair Assessment Sheet'!T54 -> 40094200 | K24: ='Repair Assessment Sheet'!J54 -> 0 | L24: ='Repair Assessment Sheet'!K54*200 -> 0 | M24: ='Repair Assessment Sheet'!Q54 -> 0 | N24: ='Repair Assessment Sheet'!R54 -> 0 | O24: ='Repair Assessment Sheet'!S54 -> 0
A25: 12 | B25: =$E$3 -> 87498574 | C25: ='Repair Assessment Sheet'!D55 -> 0 | D25: ='Repair Assessment Sheet'!E55 -> 0 | E25: ='Repair Assessment Sheet'!F55 -> 0 | F25: ='Repair Assessment Sheet'!G55 -> 0 | G25: ='Repair Assessment Sheet'!H55 -> 0 | J25: ='Repair Assessment Sheet'!T55 -> 87089900 | K25: ='Repair Assessment Sheet'!J55 -> 0 | L25: ='Repair Assessment Sheet'!K55*200 -> 0 | M25: ='Repair Assessment Sheet'!Q55 -> 0 | N25: ='Repair Assessment Sheet'!R55 -> 0 | O25: ='Repair Assessment Sheet'!S55 -> 0
A26: 13 | B26: =$E$3 -> 87498574 | C26: ='Repair Assessment Sheet'!#REF! -> #REF! | D26: ='Repair Assessment Sheet'!#REF! -> #REF! | E26: ='Repair Assessment Sheet'!#REF! -> #REF! | F26: ='Repair Assessment Sheet'!#REF! -> #REF! | G26: ='Repair Assessment Sheet'!#REF! -> #REF! | J26: ='Repair Assessment Sheet'!#REF! -> #REF! | K26: ='Repair Assessment Sheet'!#REF! -> #REF! | L26: ='Repair Assessment Sheet'!#REF!*200 -> #REF! | M26: ='Repair Assessment Sheet'!#REF! -> #REF! | N26: ='Repair Assessment Sheet'!#REF! -> #REF! | O26: ='Repair Assessment Sheet'!#REF! -> #REF!
A27: 14 | B27: =$E$3 -> 87498574 | C27: ='Repair Assessment Sheet'!D56 -> 0 | D27: ='Repair Assessment Sheet'!E56 -> 0 | E27: ='Repair Assessment Sheet'!F56 -> 0 | F27: ='Repair Assessment Sheet'!G56 -> 0 | G27: ='Repair Assessment Sheet'!H56 -> 0 | J27: ='Repair Assessment Sheet'!T56 -> 85115000 | K27: ='Repair Assessment Sheet'!J56 -> 0 | L27: ='Repair Assessment Sheet'!K56*200 -> 0 | M27: ='Repair Assessment Sheet'!Q56 -> 0 | N27: ='Repair Assessment Sheet'!R56 -> 0 | O27: ='Repair Assessment Sheet'!S56 -> 0
A28: 15 | B28: =$E$3 -> 87498574 | C28: ='Repair Assessment Sheet'!D57 -> 0 | D28: ='Repair Assessment Sheet'!E57 -> 0 | E28: ='Repair Assessment Sheet'!F57 -> 0 | F28: ='Repair Assessment Sheet'!G57 -> 0 | G28: ='Repair Assessment Sheet'!H57 -> 0 | J28: ='Repair Assessment Sheet'!T57 -> 84818090 | K28: ='Repair Assessment Sheet'!J57 -> 0 | L28: ='Repair Assessment Sheet'!K57*200 -> 0 | M28: ='Repair Assessment Sheet'!Q57 -> 0 | N28: ='Repair Assessment Sheet'!R57 -> 0 | O28: ='Repair Assessment Sheet'!S57 -> 0
A29: 16 | B29: =$E$3 -> 87498574 | C29: ='Repair Assessment Sheet'!D58 -> 0 | D29: ='Repair Assessment Sheet'!E58 -> 0 | E29: ='Repair Assessment Sheet'!F58 -> 0 | F29: ='Repair Assessment Sheet'!G58 -> 0 | G29: ='Repair Assessment Sheet'!H58 -> 0 | J29: ='Repair Assessment Sheet'!T58 -> 87089900 | K29: ='Repair Assessment Sheet'!J58 -> 0 | L29: ='Repair Assessment Sheet'!K58*200 -> 0 | M29: ='Repair Assessment Sheet'!Q58 -> 0 | N29: ='Repair Assessment Sheet'!R58 -> 0 | O29: ='Repair Assessment Sheet'!S58 -> 0
A30: 17 | B30: =$E$3 -> 87498574 | C30: ='Repair Assessment Sheet'!D59 -> 0 | D30: ='Repair Assessment Sheet'!E59 -> 0 | E30: ='Repair Assessment Sheet'!F59 -> 0 | F30: ='Repair Assessment Sheet'!G59 -> 0 | G30: ='Repair Assessment Sheet'!H59 -> 0 | J30: ='Repair Assessment Sheet'!T59 -> 84099990 | K30: ='Repair Assessment Sheet'!J59 -> 0 | L30: ='Repair Assessment Sheet'!K59*200 -> 0 | M30: ='Repair Assessment Sheet'!Q59 -> 0 | N30: ='Repair Assessment Sheet'!R59 -> 0 | O30: ='Repair Assessment Sheet'!S59 -> 0
A31: 18 | B31: =$E$3 -> 87498574 | C31: ='Repair Assessment Sheet'!D60 -> 0 | D31: ='Repair Assessment Sheet'!E60 -> 0 | E31: ='Repair Assessment Sheet'!F60 -> 0 | F31: ='Repair Assessment Sheet'!G60 -> 0 | G31: ='Repair Assessment Sheet'!H60 -> 0 | J31: ='Repair Assessment Sheet'!T60 -> 73269099 | K31: ='Repair Assessment Sheet'!J60 -> 0 | L31: ='Repair Assessment Sheet'!K60*200 -> 0 | M31: ='Repair Assessment Sheet'!Q60 -> 0 | N31: ='Repair Assessment Sheet'!R60 -> 0 | O31: ='Repair Assessment Sheet'!S60 -> 0
A32: 19 | B32: =$E$3 -> 87498574 | C32: ='Repair Assessment Sheet'!D61 -> 0 | D32: ='Repair Assessment Sheet'!E61 -> 0 | E32: ='Repair Assessment Sheet'!F61 -> 0 | F32: ='Repair Assessment Sheet'!G61 -> 0 | G32: ='Repair Assessment Sheet'!H61 -> 0 | J32: ='Repair Assessment Sheet'!T61 -> 40169990 | K32: ='Repair Assessment Sheet'!J61 -> 0 | L32: ='Repair Assessment Sheet'!K61*200 -> 0 | M32: ='Repair Assessment Sheet'!Q61 -> 0 | N32: ='Repair Assessment Sheet'!R61 -> 0 | O32: ='Repair Assessment Sheet'!S61 -> 0
A33: 20 | B33: =$E$3 -> 87498574 | C33: ='Repair Assessment Sheet'!D62 -> 0 | D33: ='Repair Assessment Sheet'!E62 -> 0 | E33: ='Repair Assessment Sheet'!F62 -> 0 | F33: ='Repair Assessment Sheet'!G62 -> 0 | G33: ='Repair Assessment Sheet'!H62 -> 0 | J33: ='Repair Assessment Sheet'!T62 -> 40169990 | K33: ='Repair Assessment Sheet'!J62 -> 0 | L33: ='Repair Assessment Sheet'!K62*200 -> 0 | M33: ='Repair Assessment Sheet'!Q62 -> 0 | N33: ='Repair Assessment Sheet'!R62 -> 0 | O33: ='Repair Assessment Sheet'!S62 -> 0
A34: 21 | B34: =$E$3 -> 87498574 | C34: ='Repair Assessment Sheet'!D63 -> 0 | D34: ='Repair Assessment Sheet'!E63 -> 0 | E34: ='Repair Assessment Sheet'!F63 -> 0 | F34: ='Repair Assessment Sheet'!G63 -> 0 | G34: ='Repair Assessment Sheet'!H63 -> 0 | J34: ='Repair Assessment Sheet'!T63 -> 87089900 | K34: ='Repair Assessment Sheet'!J63 -> 0 | L34: ='Repair Assessment Sheet'!K63*200 -> 0 | M34: ='Repair Assessment Sheet'!Q63 -> 0 | N34: ='Repair Assessment Sheet'!R63 -> 0 | O34: ='Repair Assessment Sheet'!S63 -> 0
A35: 22 | B35: =$E$3 -> 87498574 | C35: ='Repair Assessment Sheet'!#REF! -> #REF! | D35: ='Repair Assessment Sheet'!#REF! -> #REF! | E35: ='Repair Assessment Sheet'!#REF! -> #REF! | F35: ='Repair Assessment Sheet'!#REF! -> #REF! | G35: ='Repair Assessment Sheet'!#REF! -> #REF! | J35: ='Repair Assessment Sheet'!#REF! -> #REF! | K35: ='Repair Assessment Sheet'!#REF! -> #REF! | L35: ='Repair Assessment Sheet'!#REF!*200 -> #REF! | M35: ='Repair Assessment Sheet'!#REF! -> #REF! | N35: ='Repair Assessment Sheet'!#REF! -> #REF! | O35: ='Repair Assessment Sheet'!#REF! -> #REF!
A36: 23 | B36: =$E$3 -> 87498574 | C36: ='Repair Assessment Sheet'!#REF! -> #REF! | D36: ='Repair Assessment Sheet'!#REF! -> #REF! | E36: ='Repair Assessment Sheet'!#REF! -> #REF! | F36: ='Repair Assessment Sheet'!#REF! -> #REF! | G36: ='Repair Assessment Sheet'!#REF! -> #REF! | J36: ='Repair Assessment Sheet'!#REF! -> #REF! | K36: ='Repair Assessment Sheet'!#REF! -> #REF! | L36: ='Repair Assessment Sheet'!#REF!*200 -> #REF! | M36: ='Repair Assessment Sheet'!#REF! -> #REF! | N36: ='Repair Assessment Sheet'!#REF! -> #REF! | O36: ='Repair Assessment Sheet'!#REF! -> #REF!
A37: 24 | B37: =$E$3 -> 87498574 | C37: ='Repair Assessment Sheet'!#REF! -> #REF! | D37: ='Repair Assessment Sheet'!#REF! -> #REF! | E37: ='Repair Assessment Sheet'!#REF! -> #REF! | F37: ='Repair Assessment Sheet'!#REF! -> #REF! | G37: ='Repair Assessment Sheet'!#REF! -> #REF! | J37: ='Repair Assessment Sheet'!#REF! -> #REF! | K37: ='Repair Assessment Sheet'!#REF! -> #REF! | L37: ='Repair Assessment Sheet'!#REF!*200 -> #REF! | M37: ='Repair Assessment Sheet'!#REF! -> #REF! | N37: ='Repair Assessment Sheet'!#REF! -> #REF! | O37: ='Repair Assessment Sheet'!#REF! -> #REF!
A38: 25 | B38: =$E$3 -> 87498574 | C38: ='Repair Assessment Sheet'!#REF! -> #REF! | D38: ='Repair Assessment Sheet'!#REF! -> #REF! | E38: ='Repair Assessment Sheet'!#REF! -> #REF! | F38: ='Repair Assessment Sheet'!#REF! -> #REF! | G38: ='Repair Assessment Sheet'!#REF! -> #REF! | J38: ='Repair Assessment Sheet'!#REF! -> #REF! | K38: ='Repair Assessment Sheet'!#REF! -> #REF! | L38: ='Repair Assessment Sheet'!#REF!*200 -> #REF! | M38: ='Repair Assessment Sheet'!#REF! -> #REF! | N38: ='Repair Assessment Sheet'!#REF! -> #REF! | O38: ='Repair Assessment Sheet'!#REF! -> #REF!
A39: 26 | B39: =$E$3 -> 87498574 | C39: ='Repair Assessment Sheet'!#REF! -> #REF! | D39: ='Repair Assessment Sheet'!#REF! -> #REF! | E39: ='Repair Assessment Sheet'!#REF! -> #REF! | F39: ='Repair Assessment Sheet'!#REF! -> #REF! | G39: ='Repair Assessment Sheet'!#REF! -> #REF! | J39: ='Repair Assessment Sheet'!#REF! -> #REF! | K39: ='Repair Assessment Sheet'!#REF! -> #REF! | L39: ='Repair Assessment Sheet'!#REF!*200 -> #REF! | M39: ='Repair Assessment Sheet'!#REF! -> #REF! | N39: ='Repair Assessment Sheet'!#REF! -> #REF! | O39: ='Repair Assessment Sheet'!#REF! -> #REF!
A40: 27 | B40: =$E$3 -> 87498574 | C40: ='Repair Assessment Sheet'!#REF! -> #REF! | D40: ='Repair Assessment Sheet'!#REF! -> #REF! | E40: ='Repair Assessment Sheet'!#REF! -> #REF! | F40: ='Repair Assessment Sheet'!#REF! -> #REF! | G40: ='Repair Assessment Sheet'!#REF! -> #REF! | J40: ='Repair Assessment Sheet'!#REF! -> #REF! | K40: ='Repair Assessment Sheet'!#REF! -> #REF! | L40: ='Repair Assessment Sheet'!#REF!*200 -> #REF! | M40: ='Repair Assessment Sheet'!#REF! -> #REF! | N40: ='Repair Assessment Sheet'!#REF! -> #REF! | O40: ='Repair Assessment Sheet'!#REF! -> #REF!
A41: 28 | B41: =$E$3 -> 87498574 | C41: ='Repair Assessment Sheet'!#REF! -> #REF! | D41: ='Repair Assessment Sheet'!#REF! -> #REF! | E41: ='Repair Assessment Sheet'!#REF! -> #REF! | F41: ='Repair Assessment Sheet'!#REF! -> #REF! | G41: ='Repair Assessment Sheet'!#REF! -> #REF! | J41: ='Repair Assessment Sheet'!#REF! -> #REF! | K41: ='Repair Assessment Sheet'!#REF! -> #REF! | L41: ='Repair Assessment Sheet'!#REF!*200 -> #REF! | M41: ='Repair Assessment Sheet'!#REF! -> #REF! | N41: ='Repair Assessment Sheet'!#REF! -> #REF! | O41: ='Repair Assessment Sheet'!#REF! -> #REF!
A42: 29 | B42: =$E$3 -> 87498574 | C42: ='Repair Assessment Sheet'!D69 -> 0 | D42: ='Repair Assessment Sheet'!E69 -> 0 | E42: ='Repair Assessment Sheet'!F69 -> 0 | F42: ='Repair Assessment Sheet'!G69 -> 0 | G42: ='Repair Assessment Sheet'!H69 -> 0 | J42: ='Repair Assessment Sheet'!T69 -> 0 | K42: ='Repair Assessment Sheet'!J69 -> 0 | L42: ='Repair Assessment Sheet'!K69*200 -> 0 | M42: ='Repair Assessment Sheet'!Q69 -> 0 | N42: ='Repair Assessment Sheet'!R69 -> 0 | O42: ='Repair Assessment Sheet'!S69 -> 0
A43: 30 | B43: =$E$3 -> 87498574 | C43: ='Repair Assessment Sheet'!D70 -> 0 | D43: ='Repair Assessment Sheet'!E70 -> 0 | E43: ='Repair Assessment Sheet'!F70 -> 0 | F43: ='Repair Assessment Sheet'!G70 -> 0 | G43: ='Repair Assessment Sheet'!H70 -> 0 | J43: ='Repair Assessment Sheet'!T70 -> 0 | K43: ='Repair Assessment Sheet'!J70 -> 0 | L43: ='Repair Assessment Sheet'!K70*200 -> 0 | M43: ='Repair Assessment Sheet'!Q70 -> 0 | N43: ='Repair Assessment Sheet'!R70 -> 0 | O43: ='Repair Assessment Sheet'!S70 -> 0
A44: 31 | B44: =$E$3 -> 87498574 | C44: ='Repair Assessment Sheet'!D71 -> 0 | D44: ='Repair Assessment Sheet'!E71 -> 0 | E44: ='Repair Assessment Sheet'!F71 -> 0 | F44: ='Repair Assessment Sheet'!G71 -> 0 | G44: ='Repair Assessment Sheet'!H71 -> 0 | J44: ='Repair Assessment Sheet'!T71 -> 0 | K44: ='Repair Assessment Sheet'!J71 -> 0 | L44: ='Repair Assessment Sheet'!K71*200 -> 0 | M44: ='Repair Assessment Sheet'!Q71 -> 0 | N44: ='Repair Assessment Sheet'!R71 -> 0 | O44: ='Repair Assessment Sheet'!S71 -> 0
A45: 32 | B45: =$E$3 -> 87498574 | C45: ='Repair Assessment Sheet'!D72 -> 0 | D45: ='Repair Assessment Sheet'!E72 -> 0 | E45: ='Repair Assessment Sheet'!F72 -> 0 | F45: ='Repair Assessment Sheet'!G72 -> 0 | G45: ='Repair Assessment Sheet'!H72 -> 0 | J45: ='Repair Assessment Sheet'!T72 -> 0 | K45: ='Repair Assessment Sheet'!J72 -> 0 | L45: ='Repair Assessment Sheet'!K72*200 -> 0 | M45: ='Repair Assessment Sheet'!Q72 -> 0 | N45: ='Repair Assessment Sheet'!R72 -> 0 | O45: ='Repair Assessment Sheet'!S72 -> 0
A46: 33 | B46: =$E$3 -> 87498574 | C46: ='Repair Assessment Sheet'!D73 -> 0 | D46: ='Repair Assessment Sheet'!E73 -> 0 | E46: ='Repair Assessment Sheet'!F73 -> 0 | F46: ='Repair Assessment Sheet'!G73 -> 0 | G46: ='Repair Assessment Sheet'!H73 -> 0 | J46: ='Repair Assessment Sheet'!T73 -> 0 | K46: ='Repair Assessment Sheet'!J73 -> 0 | L46: ='Repair Assessment Sheet'!K73*200 -> 0 | M46: ='Repair Assessment Sheet'!Q73 -> 0 | N46: ='Repair Assessment Sheet'!R73 -> 0 | O46: ='Repair Assessment Sheet'!S73 -> 0
A47: 34 | B47: =$E$3 -> 87498574 | C47: ='Repair Assessment Sheet'!D74 -> 0 | D47: ='Repair Assessment Sheet'!E74 -> Net Amout in INR | E47: ='Repair Assessment Sheet'!F74 -> SGST AM | F47: ='Repair Assessment Sheet'!G74 -> CGST AM | G47: ='Repair Assessment Sheet'!H74 -> Discount | J47: ='Repair Assessment Sheet'!T74 -> 0 | K47: ='Repair Assessment Sheet'!J74 -> Net Payble INR | L47: ='Repair Assessment Sheet'!K74*200 -> 0 | M47: ='Repair Assessment Sheet'!Q74 -> 0 | N47: ='Repair Assessment Sheet'!R74 -> 0 | O47: ='Repair Assessment Sheet'!S74 -> 0
A48: 35 | B48: =$E$3 -> 87498574 | C48: ='Repair Assessment Sheet'!D75 -> 0 | D48: ='Repair Assessment Sheet'!E75 -> 0 | E48: ='Repair Assessment Sheet'!F75 -> 0 | F48: ='Repair Assessment Sheet'!G75 -> 0 | G48: ='Repair Assessment Sheet'!H75 -> 0 | J48: ='Repair Assessment Sheet'!T75 -> 0 | K48: ='Repair Assessment Sheet'!J75 -> 0 | L48: ='Repair Assessment Sheet'!K75*200 -> 0 | M48: ='Repair Assessment Sheet'!Q75 -> 0 | N48: ='Repair Assessment Sheet'!R75 -> 0 | O48: ='Repair Assessment Sheet'!S75 -> 0
A49: 36 | B49: =$E$3 -> 87498574 | C49: ='Repair Assessment Sheet'!D76 -> 0 | D49: ='Repair Assessment Sheet'!E76 -> 0 | E49: ='Repair Assessment Sheet'!F76 -> 0 | F49: ='Repair Assessment Sheet'!G76 -> 0 | G49: ='Repair Assessment Sheet'!H76 -> 0 | J49: ='Repair Assessment Sheet'!T76 -> 0 | K49: ='Repair Assessment Sheet'!J76 -> 0 | L49: ='Repair Assessment Sheet'!K76*200 -> 0 | M49: ='Repair Assessment Sheet'!Q76 -> 0 | N49: ='Repair Assessment Sheet'!R76 -> 0 | O49: ='Repair Assessment Sheet'!S76 -> 0
A50: 37 | B50: =$E$3 -> 87498574 | C50: ='Repair Assessment Sheet'!D77 -> 0 | D50: ='Repair Assessment Sheet'!E77 -> 0 | E50: ='Repair Assessment Sheet'!F77 -> 0 | F50: ='Repair Assessment Sheet'!G77 -> 0 | G50: ='Repair Assessment Sheet'!H77 -> 0 | J50: ='Repair Assessment Sheet'!T77 -> 0 | K50: ='Repair Assessment Sheet'!J77 -> 0 | L50: ='Repair Assessment Sheet'!K77*200 -> 0 | M50: ='Repair Assessment Sheet'!Q77 -> 0 | N50: ='Repair Assessment Sheet'!R77 -> 0 | O50: ='Repair Assessment Sheet'!S77 -> 0
A51: 38 | B51: =$E$3 -> 87498574 | C51: ='Repair Assessment Sheet'!D78 -> 0 | D51: ='Repair Assessment Sheet'!E78 -> 0 | E51: ='Repair Assessment Sheet'!F78 -> 0 | F51: ='Repair Assessment Sheet'!G78 -> 0 | G51: ='Repair Assessment Sheet'!H78 -> 0 | J51: ='Repair Assessment Sheet'!T78 -> 0 | K51: ='Repair Assessment Sheet'!J78 -> 0 | L51: ='Repair Assessment Sheet'!K78*200 -> 0 | M51: ='Repair Assessment Sheet'!Q78 -> 0 | N51: ='Repair Assessment Sheet'!R78 -> 0 | O51: ='Repair Assessment Sheet'!S78 -> 1000
A52: 39 | B52: =$E$3 -> 87498574 | C52: ='Repair Assessment Sheet'!D79 -> 0 | D52: ='Repair Assessment Sheet'!E79 -> 0 | E52: ='Repair Assessment Sheet'!F79 -> SGST IN % | F52: ='Repair Assessment Sheet'!G79 -> CGST IN % | G52: ='Repair Assessment Sheet'!H79 -> 0 | J52: ='Repair Assessment Sheet'!T79 -> 0 | K52: ='Repair Assessment Sheet'!J79 -> 0 | L52: ='Repair Assessment Sheet'!K79*200 -> 0 | M52: ='Repair Assessment Sheet'!Q79 -> 0 | N52: ='Repair Assessment Sheet'!R79 -> 0 | O52: ='Repair Assessment Sheet'!S79 -> 0
A53: 40 | B53: =$E$3 -> 87498574 | C53: ='Repair Assessment Sheet'!D80 -> 0 | D53: ='Repair Assessment Sheet'!E80 -> 0 | E53: ='Repair Assessment Sheet'!F80 -> 9 | F53: ='Repair Assessment Sheet'!G80 -> 9 | G53: ='Repair Assessment Sheet'!H80 -> 0 | J53: ='Repair Assessment Sheet'!T80 -> 0 | K53: ='Repair Assessment Sheet'!J80 -> 0 | L53: ='Repair Assessment Sheet'!K80*200 -> 0 | M53: ='Repair Assessment Sheet'!Q80 -> 0 | N53: ='Repair Assessment Sheet'!R80 -> 0 | O53: ='Repair Assessment Sheet'!S80 -> 1000
... A98: 85 | B98: =$E$3 -> 87498574 | C98: ='Repair Assessment Sheet'!D125 -> 0 | D98: ='Repair Assessment Sheet'!E125 -> 0 | E98: ='Repair Assessment Sheet'!F125 -> 0 | F98: ='Repair Assessment Sheet'!G125 -> 0 | G98: ='Repair Assessment Sheet'!H125 -> 0 | J98: ='Repair Assessment Sheet'!T125 -> 0 | K98: ='Repair Assessment Sheet'!J125 -> 0 | L98: ='Repair Assessment Sheet'!K125*200 -> 0 | M98: ='Repair Assessment Sheet'!Q125 -> 0 | N98: ='Repair Assessment Sheet'!R125 -> 0 | O98: ='Repair Assessment Sheet'!S125 -> 0
A99: 86 | B99: =E88 -> 0 | C99: ='Repair Assessment Sheet'!D126 -> Repair/ Replace | D99: ='Repair Assessment Sheet'!E126 -> Description | E99: ='Repair Assessment Sheet'!F126 -> 0 | F99: ='Repair Assessment Sheet'!G126 -> 0 | G99: ='Repair Assessment Sheet'!H126 -> 0 | J99: ='Repair Assessment Sheet'!T126 -> 0 | K99: ='Repair Assessment Sheet'!J126 -> Parts@list (A) | L99: ='Repair Assessment Sheet'!K126*200 -> 0 | M99: ='Repair Assessment Sheet'!Q126 -> Labour Remove Refit | N99: ='Repair Assessment Sheet'!R126 -> Labour Repair | O99: ='Repair Assessment Sheet'!S126 -> Paint
A100: 87 | B100: =E89 -> 0 | C100: ='Repair Assessment Sheet'!D127 -> 0 | D100: ='Repair Assessment Sheet'!E127 -> Material | E100: ='Repair Assessment Sheet'!F127 -> 0 | F100: ='Repair Assessment Sheet'!G127 -> Side | G100: ='Repair Assessment Sheet'!H127 -> Section | J100: ='Repair Assessment Sheet'!T127 -> 0 | K100: ='Repair Assessment Sheet'!J127 -> 0 | L100: ='Repair Assessment Sheet'!K127*200 -> 0 | M100: ='Repair Assessment Sheet'!Q127 -> 0 | N100: ='Repair Assessment Sheet'!R127 -> 0 | O100: ='Repair Assessment Sheet'!S127 -> 0
A101: 88 | B101: =E90 -> 0 | C101: ='Repair Assessment Sheet'!D128 -> 0 | D101: ='Repair Assessment Sheet'!E128 -> Plastic/Rubber | E101: ='Repair Assessment Sheet'!F128 -> 0 | F101: ='Repair Assessment Sheet'!G128 -> 0 | G101: ='Repair Assessment Sheet'!H128 -> 0 | J101: ='Repair Assessment Sheet'!T128 -> 0 | K101: ='Repair Assessment Sheet'!J128 -> 0 | L101: ='Repair Assessment Sheet'!K128*200 -> 0 | M101: ='Repair Assessment Sheet'!Q128 -> 0 | N101: ='Repair Assessment Sheet'!R128 -> 0 | O101: ='Repair Assessment Sheet'!S128 -> 0
A102: 89 | B102: =E91 -> 0 | C102: ='Repair Assessment Sheet'!D129 -> 0 | D102: ='Repair Assessment Sheet'!E129 -> 0 | E102: ='Repair Assessment Sheet'!F129 -> 0 | F102: ='Repair Assessment Sheet'!G129 -> 0 | G102: ='Repair Assessment Sheet'!H129 -> 0 | J102: ='Repair Assessment Sheet'!T129 -> 0 | K102: ='Repair Assessment Sheet'!J129 -> 0 | L102: ='Repair Assessment Sheet'!K129*200 -> 0 | M102: ='Repair Assessment Sheet'!Q129 -> 0 | N102: ='Repair Assessment Sheet'!R129 -> 0 | O102: ='Repair Assessment Sheet'!S129 -> 0
A103: 90 | B103: =E92 -> 0 | C103: ='Repair Assessment Sheet'!D130 -> 0 | D103: ='Repair Assessment Sheet'!E130 -> 0 | E103: ='Repair Assessment Sheet'!F130 -> 0 | F103: ='Repair Assessment Sheet'!G130 -> 0 | G103: ='Repair Assessment Sheet'!H130 -> 0 | J103: ='Repair Assessment Sheet'!T130 -> 0 | K103: ='Repair Assessment Sheet'!J130 -> 0 | L103: ='Repair Assessment Sheet'!K130*200 -> 0 | M103: ='Repair Assessment Sheet'!Q130 -> 0 | N103: ='Repair Assessment Sheet'!R130 -> 0 | O103: ='Repair Assessment Sheet'!S130 -> 0
A104: 91 | B104: =E93 -> 0 | C104: ='Repair Assessment Sheet'!D131 -> 0 | D104: ='Repair Assessment Sheet'!E131 -> 0 | E104: ='Repair Assessment Sheet'!F131 -> 0 | F104: ='Repair Assessment Sheet'!G131 -> 0 | G104: ='Repair Assessment Sheet'!H131 -> 0 | J104: ='Repair Assessment Sheet'!T131 -> 0 | K104: ='Repair Assessment Sheet'!J131 -> 0 | L104: ='Repair Assessment Sheet'!K131*200 -> 0 | M104: ='Repair Assessment Sheet'!Q131 -> 0 | N104: ='Repair Assessment Sheet'!R131 -> 0 | O104: ='Repair Assessment Sheet'!S131 -> 0
A105: 92 | B105: =E94 -> 0 | C105: ='Repair Assessment Sheet'!D132 -> 0 | D105: ='Repair Assessment Sheet'!E132 -> 0 | E105: ='Repair Assessment Sheet'!F132 -> 0 | F105: ='Repair Assessment Sheet'!G132 -> 0 | G105: ='Repair Assessment Sheet'!H132 -> 0 | J105: ='Repair Assessment Sheet'!T132 -> 0 | K105: ='Repair Assessment Sheet'!J132 -> 0 | L105: ='Repair Assessment Sheet'!K132*200 -> 0 | M105: ='Repair Assessment Sheet'!Q132 -> 0 | N105: ='Repair Assessment Sheet'!R132 -> 0 | O105: ='Repair Assessment Sheet'!S132 -> 0
A106: 93 | B106: =E95 -> 0 | C106: ='Repair Assessment Sheet'!D133 -> 0 | D106: ='Repair Assessment Sheet'!E133 -> 0 | E106: ='Repair Assessment Sheet'!F133 -> 0 | F106: ='Repair Assessment Sheet'!G133 -> 0 | G106: ='Repair Assessment Sheet'!H133 -> 0 | J106: ='Repair Assessment Sheet'!T133 -> 0 | K106: ='Repair Assessment Sheet'!J133 -> 0 | L106: ='Repair Assessment Sheet'!K133*200 -> 0 | M106: ='Repair Assessment Sheet'!Q133 -> 0 | N106: ='Repair Assessment Sheet'!R133 -> 0 | O106: ='Repair Assessment Sheet'!S133 -> 0
A107: 94 | B107: =E96 -> 0 | C107: ='Repair Assessment Sheet'!D134 -> 0 | D107: ='Repair Assessment Sheet'!E134 -> 0 | E107: ='Repair Assessment Sheet'!F134 -> 0 | F107: ='Repair Assessment Sheet'!G134 -> 0 | G107: ='Repair Assessment Sheet'!H134 -> 0 | J107: ='Repair Assessment Sheet'!T134 -> 0 | K107: ='Repair Assessment Sheet'!J134 -> 0 | L107: ='Repair Assessment Sheet'!K134*200 -> 0 | M107: ='Repair Assessment Sheet'!Q134 -> 0 | N107: ='Repair Assessment Sheet'!R134 -> 0 | O107: ='Repair Assessment Sheet'!S134 -> 0
A108: 95 | B108: =E97 -> 0 | C108: ='Repair Assessment Sheet'!D135 -> 0 | D108: ='Repair Assessment Sheet'!E135 -> 0 | E108: ='Repair Assessment Sheet'!F135 -> 0 | F108: ='Repair Assessment Sheet'!G135 -> 0 | G108: ='Repair Assessment Sheet'!H135 -> 0 | J108: ='Repair Assessment Sheet'!T135 -> 0 | K108: ='Repair Assessment Sheet'!J135 -> 0 | L108: ='Repair Assessment Sheet'!K135*200 -> 0 | M108: ='Repair Assessment Sheet'!Q135 -> 0 | N108: ='Repair Assessment Sheet'!R135 -> 0 | O108: ='Repair Assessment Sheet'!S135 -> 0
A109: 96 | B109: =E98 -> 0 | C109: ='Repair Assessment Sheet'!D136 -> 0 | D109: ='Repair Assessment Sheet'!E136 -> 0 | E109: ='Repair Assessment Sheet'!F136 -> 0 | F109: ='Repair Assessment Sheet'!G136 -> 0 | G109: ='Repair Assessment Sheet'!H136 -> 0 | J109: ='Repair Assessment Sheet'!T136 -> 0 | K109: ='Repair Assessment Sheet'!J136 -> 0 | L109: ='Repair Assessment Sheet'!K136*200 -> 0 | M109: ='Repair Assessment Sheet'!Q136 -> 0 | N109: ='Repair Assessment Sheet'!R136 -> 0 | O109: ='Repair Assessment Sheet'!S136 -> 0
A110: 97 | B110: =E99 -> 0 | C110: ='Repair Assessment Sheet'!D137 -> 0 | D110: ='Repair Assessment Sheet'!E137 -> 0 | E110: ='Repair Assessment Sheet'!F137 -> 0 | F110: ='Repair Assessment Sheet'!G137 -> 0 | G110: ='Repair Assessment Sheet'!H137 -> 0 | J110: ='Repair Assessment Sheet'!T137 -> 0 | K110: ='Repair Assessment Sheet'!J137 -> 0 | L110: ='Repair Assessment Sheet'!K137*200 -> 0 | M110: ='Repair Assessment Sheet'!Q137 -> 0 | N110: ='Repair Assessment Sheet'!R137 -> 0 | O110: ='Repair Assessment Sheet'!S137 -> 0
... A130: 117 | B130: =E119 -> 0 | C130: ='Repair Assessment Sheet'!D157 -> 0 | D130: ='Repair Assessment Sheet'!E157 -> 0 | E130: ='Repair Assessment Sheet'!F157 -> 0 | F130: ='Repair Assessment Sheet'!G157 -> 0 | G130: ='Repair Assessment Sheet'!H157 -> 0 | J130: ='Repair Assessment Sheet'!T157 -> 0 | K130: ='Repair Assessment Sheet'!J157 -> 0 | L130: ='Repair Assessment Sheet'!K157*200 -> 0 | M130: ='Repair Assessment Sheet'!Q157 -> 0 | N130: ='Repair Assessment Sheet'!R157 -> 0 | O130: ='Repair Assessment Sheet'!S157 -> 0
A131: 118
A132: 119
A133: 120
A134: 121
A135: 122
A136: 123
A137: 124
A138: 125
A139: 126
A140: 127
A141: 128
A142: 129
... A513: 500

Sheet Bill
A1: KONCEPT AUTOMOBILES PVT. LTD.
A2: B1/G5 MCIA MATHURA ROAD NEW DELHI, -110044
A3: Dealer GSTIN : 07AACCK8444R1ZT Tax Invoice (Invoice issued under Rule 46 of CGST/SGST Rules, 2017.) | U3: Dealer State Code : 07
A4: BILL TO | H4: SHIP TO | O4: VEHICLE INFO | U4: INVOICE INFO
A5: Cust. GSTIN : 07AABCT3518Q1ZY State Cd. : 07 Cust. Code : S10 Name : M/S. TATA AIG General Insurance Company Ltd. Address : Plot No 22 2nd Floor Community Centre New Friends Colony, New Delhi NEW DELHI ,New Delhi - 110025 Delhi State : Delhi Phone : Pan No. : | H5: Cust. GSTIN : 07AABCT3518Q1ZY State Cd. : 07 Cust. Code : S10 Cust.Name : M/S. TATA AIG General Insurance Company Ltd. Address : Plot No 22 2nd Floor Community Centre New Friends Colony, New Delhi NEW DELHI ,New Delhi - 110025 Delhi State : Delhi Phone : Pan No. : | O5: Reg No : UP16CH7070 Model : MAHINDRA XUV500 FWD W9 WTH0 NP Chass No : K6G11187 Engine No. : XXXXX Sold Date : 14-SEP-19 00:00:00 Pay Mode : Credit Key Account : Leasing Client : K_Part%: 0 K_Labour%:0 Mileage : 30503 | U5: GST Invc No. : INS23S001237 GST Invc Dt : 18-FEB-23 18:25:56 RO No. : RO23S001581 RO Date : 03-FEB-23 11:16:00 SA Name : RAHUL KUMAR Service Type : ACCIDENTAL Sale Type : Within State Voucher ID : Dealer Pan : AACCK8444R Process Name : RO Bill Place of Supply : Delhi
A6: IRN : 0ec81356ed37f3008eaad42d4806ff9dde0697e8974be8046d278b04c642da3d
A7: Sr.N o. | C7: Part No/Lab code | E7: Part/Lab Description | I7: HSN/SAC | K7: Qty. | L7: Unit | M7: Rate(per item) | Q7: Total | S7: Disc. | T7: Taxable value | U7: CGST | W7: SGST
U8: Rate% | V8: Amnt. | W8: Rate% | X8: Amnt.
C9: Part Details :
A10: 1 | C10: R134 | E10: Local Spare part Oil & | I10: 87089900 | K10: 10 | L10: G | M10: 140.63 | Q10: 1406.3 | S10: 0 | T10: 1406.3 | U10: 14 | V10: 196.88 | W10: 14 | X10: 196.88
A11: 2 | C11: 0102DAW00110N | E11: ASSY SPLASH SHIELD | I11: 87089900 | K11: 1 | L11: EA | M11: 1152.34 | Q11: 1152.34 | S11: 0 | T11: 1152.34 | U11: 14 | V11: 161.33 | W11: 14 | X11: 161.33
A12: 3 | C12: 0304AAM00150N | E12: ASSY COND RAD FAN | I12: 84159000 | K12: 1 | L12: EA | M12: 23124.58 | Q12: 23124.58 | S12: 0 | T12: 23124.58 | U12: 9 | V12: 2081.21 | W12: 9 | X12: 2081.21
A13: 4 | C13: 0304AAM01910N | E13: SEALS RADIATOR TOP | I13: 40169390 | K13: 1 | L13: EA | M13: 180.51 | Q13: 180.51 | S13: 0 | T13: 180.51 | U13: 9 | V13: 16.25 | W13: 9 | X13: 16.25
A14: 5 | C14: 2301AAW01440F | E14: COVER ASSY IP TOP | I14: 39269099 | K14: 1 | L14: EA | M14: 5208.47 | Q14: 5208.47 | S14: 0 | T14: 5208.47 | U14: 9 | V14: 468.76 | W14: 9 | X14: 468.76
A15: 6 | C15: OIL134 | E15: Local Spare Part | I15: 34031900 | K15: 1 | L15: ML | M15: 381.36 | Q15: 381.36 | S15: 0 | T15: 381.36 | U15: 9 | V15: 34.32 | W15: 9 | X15: 34.32
A16: 7 | C16: 0107DAG00110N | E16: WIND SHIELD PASTING | I16: 87089900 | K16: 2 | L16: EA | M16: 1476.56 | Q16: 2953.12 | S16: 0 | T16: 2953.12 | U16: 14 | V16: 413.44 | W16: 14 | X16: 413.44
A17: 8 | C17: 2302CAW0001KT | E17: TRIM ASSY FNDR | I17: 87082900 | K17: 1 | L17: EA | M17: 5822.66 | Q17: 5822.66 | S17: 0 | T17: 5822.66 | U17: 14 | V17: 815.17 | W17: 14 | X17: 815.17
A18: 9 | C18: 0108AAW00410N | E18: GRILL ASSY FRONT | I18: 87089900 | K18: 1 | L18: EA | M18: 9127.34 | Q18: 9127.34 | S18: 0 | T18: 9127.34 | U18: 14 | V18: 1277.83 | W18: 14 | X18: 1277.83
A19: 10 | C19: 0108BAW00890N | E19: CLADDING ASSY FRT | I19: 87081090 | K19: 1 | L19: EA | M19: 148.44 | Q19: 148.44 | S19: 0 | T19: 148.44 | U19: 14 | V19: 20.78 | W19: 14 | X19: 20.78
A20: 11 | C20: 0108AAW00390N | E20: BEZEL ASSY FOG | I20: 85122010 | K20: 1 | L20: EA | M20: 591.53 | Q20: 591.53 | S20: 0 | T20: 591.53 | U20: 9 | V20: 53.24 | W20: 9 | X20: 53.24
A21: 12 | C21: 1701AAA07741N | E21: HEADLAMP ASSY LH | I21: 85122010 | K21: 1 | L21: EA | M21: 11421.19 | Q21: 11421.19 | S21: 0 | T21: 11421.19 | U21: 9 | V21: 1027.91 | W21: 9 | X21: 1027.91
... A53: 44 | C53: 0120AAW00651L | E53: SEAT BELT ASSY FRT | I53: 87082100 | K53: 1 | L53: EA | M53: 3207.03 | Q53: 3207.03 | S53: 0 | T53: 3207.03 | U53: 14 | V53: 448.98 | W53: 14 | X53: 448.98
A54: Labour Details
A56: 1 | C56: LOC-Z222 | E56: KN OPERATIONS - ACCIDENT REPAIRS | I56: 998729 | K56: - | L56: - | M56: - | Q56: 24000 | S56: 0 | T56: 24000 | U56: 9 | V56: 2160 | W56: 9 | X56: 2160
A58: Sub Total | Q58: 2,34,550.33 | S58: 0 | T58: 2,34,550.33 | U58: 25839.9 | W58: 25839.9
A59: Part Total Items : 44 | U59: Total | W59: 2,86,230.13
A60: Part Net Qty : 59 | U60: Round of Amount | W60: -0.13
A61: Rupees Two Lakh Eighty Six Thousand Two Hundred And Thirty Only Grand Total | W61: 2,86,230.00
A62: Declaration :
A63: Customer Name : ANKUSH SHARMA S/O TARLOK NATH SHARMA Customer Signature : Authorized Signature :
A64: Whether tax is Payable on reverse charges : NO
A65: Electronic Reference Number : INS23S001237 Date : 18-FEB-23 18:25:56
A67: KONCEPT AUTOMOBILES PVT. LTD.
A68: B1/G5 MCIA MATHURA ROAD NEW DELHI, -110044
A69: Dealer GSTIN : 07AACCK8444R1ZT Tax Invoice Dealer State Code : 07 (Invoice issued under Rule 46 of CGST/SGST Rules, 2017.)
B71: GST Summary
B72: Sharing % | G72: Labour | J72: Goods
B73: Central GST 14% | G73: 0 | J73: 13245
B74: Central GST 9% | G74: 0 | J74: 10434.9
B75: Central GST 9% | G75: 2160 | J75: 0
B76: State GST 14% | G76: 0 | J76: 13245
B77: State GST 9% | G77: 2160 | J77: 0
B78: State GST 9% | G78: 0 | J78: 10434.9
B79: Total | G79: 4320 | J79: 47359.8
A80: Want to give a suggestion or share a feedback about dealership experience? You can reach out to Mahindra & Mahindra Ltd Email: customercare@mahindra.com, 24x7 Toll free: 18002096006, Twitter Scan:
A84: KONCEPT AUTOMOBILES PVT. LTD.
A85: B1/G5 MCIA MATHURA ROAD NEW DELHI, -110044
A86: Dealer GSTIN : 07AACCK8444R1ZT Tax Invoice Dealer State Code : 07 (Invoice issued under Rule 46 of CGST/SGST Rules, 2017.)
A87: SATISFACTION NOTE
A88: Date : 18-FEB-2023 RO Number : RO23S001581 Model : MAHINDRA XUV500 FWD W9 WTH0 NP Vehicle Registration Number Vehicle Serial Number Engine Number UP16CH7070 K6G11187 XXXXX I have received the vehicle back in good condition and i am fully satisfied with the jobs done by M/s KONCEPT AUTOMOBILES PVT LTD - MCIA MATHURA ROAD Name : ANKUSH SHARMA S/O TARLOK NATH SHARMA Comments by customer (if any) Address : G-104 SKYTECH MATROTT APARTMENTS NEAR J M ORCHID APARTMENTS SECTOR-76 NOIDA Uttar Pradesh PIN:201301 Phone : 8800927888 8800927888
A89: Customer's Signature : Date :
A90: Pending Job (Cust Verb) in this RO
D92: Sl No | F92: Cust Verbatim | R92: Source | U92: Closing Status
D93: 1 | F93: WASHING & CLEANING | R93: System | U93: Customer Refused
A95: Work to be done (Recommended by Service Advisor)
A96: Washing / cleaning not done on the basis of customer advice
A97: GATE PASS
A98: Gate Pass No. : GTP23S001574 GP Date : 18-FEB-2023 Reg No. : UP16CH7070 Model : MAHINDRA XUV500 FWD W9 WTH0 NP | P98: RO Bill No. Bill Date INS23S001237 18-FEB-2023 RO No. RO Date RO23S001581 03-FEB-2023
A99: Customer Name & Signature | P99: Authorized Signature
